{
	"credit": "Made with Blockbench",
	"texture_size": [64, 64],
	"textures": {
		"0": "block/quinoa0",
		"2": "block/quinoa1",
		"3": "block/quinoa2",
		"4": "block/quinoa3",
		"particle": "block/quinoa1"
	},
	"elements": [
		{
			"from": [9.25, 11.8, 7.05],
			"to": [9.9, 12.15, 7.65],
			"rotation": {"angle": 0, "axis": "y", "origin": [17.1, 16.6, 15]},
			"faces": {
				"north": {"uv": [6.5, 14.25, 10, 16], "texture": "#2"},
				"east": {"uv": [6.5, 14.25, 10, 16], "texture": "#2"},
				"south": {"uv": [6.5, 14.25, 10, 16], "texture": "#2"},
				"west": {"uv": [6.5, 14.25, 10, 16], "texture": "#2"},
				"down": {"uv": [6.5, 14.25, 10, 16], "texture": "#2"}
			}
		},
		{
			"from": [9.25, 12.3, 7.05],
			"to": [9.9, 12.65, 7.65],
			"rotation": {"angle": 0, "axis": "y", "origin": [17.1, 17.1, 15]},
			"faces": {
				"north": {"uv": [6, 8, 9.5, 9.75], "texture": "#2"},
				"east": {"uv": [6, 8, 9.5, 9.75], "texture": "#2"},
				"south": {"uv": [6, 8, 9.5, 9.75], "texture": "#2"},
				"west": {"uv": [6, 8, 9.5, 9.75], "texture": "#2"}
			}
		},
		{
			"from": [9.25, 12.8, 7.05],
			"to": [9.9, 13.15, 7.65],
			"rotation": {"angle": 0, "axis": "y", "origin": [17.1, 17.6, 15]},
			"faces": {
				"north": {"uv": [5.5, 3.5, 9, 5.25], "texture": "#2"},
				"east": {"uv": [5.5, 3.5, 9, 5.25], "texture": "#2"},
				"south": {"uv": [5.5, 3.5, 9, 5.25], "texture": "#2"},
				"west": {"uv": [5.5, 3.5, 9, 5.25], "texture": "#2"}
			}
		},
		{
			"from": [9.25, 13.3, 7.05],
			"to": [9.9, 13.65, 7.65],
			"rotation": {"angle": 0, "axis": "y", "origin": [17.1, 18.1, 15]},
			"faces": {
				"north": {"uv": [5.75, 12.5, 9.25, 14.25], "texture": "#2"},
				"east": {"uv": [5.75, 12.5, 9.25, 14.25], "texture": "#2"},
				"south": {"uv": [5.75, 12.5, 9.25, 14.25], "texture": "#2"},
				"west": {"uv": [5.75, 12.5, 9.25, 14.25], "texture": "#2"}
			}
		},
		{
			"from": [9.25, 13.8, 7.05],
			"to": [9.9, 14.15, 7.65],
			"rotation": {"angle": 0, "axis": "y", "origin": [17.1, 18.6, 15]},
			"faces": {
				"north": {"uv": [5.75, 4, 9.25, 5.75], "texture": "#2"},
				"east": {"uv": [5.75, 4, 9.25, 5.75], "texture": "#2"},
				"south": {"uv": [5.75, 4, 9.25, 5.75], "texture": "#2"},
				"west": {"uv": [5.75, 4, 9.25, 5.75], "texture": "#2"}
			}
		},
		{
			"from": [9.25, 14.4, 7.05],
			"to": [9.9, 14.75, 7.65],
			"rotation": {"angle": 0, "axis": "y", "origin": [17.1, 19.2, 15]},
			"faces": {
				"north": {"uv": [5.75, 0, 9.25, 1.75], "texture": "#2"},
				"east": {"uv": [5.75, 0, 9.25, 1.75], "texture": "#2"},
				"south": {"uv": [5.75, 0, 9.25, 1.75], "texture": "#2"},
				"west": {"uv": [5.75, 0, 9.25, 1.75], "texture": "#2"},
				"up": {"uv": [5.75, 0, 9.25, 3], "texture": "#2"}
			}
		},
		{
			"from": [9.15, 12.1, 6.95],
			"to": [10, 12.45, 7.75],
			"rotation": {"angle": 0, "axis": "y", "origin": [17.1, 16.9, 15]},
			"faces": {
				"north": {"uv": [5.5, 11.75, 10.25, 13.75], "texture": "#2"},
				"east": {"uv": [5.5, 11.75, 10.25, 13.75], "texture": "#2"},
				"south": {"uv": [5.5, 11.75, 10.25, 13.75], "texture": "#2"},
				"west": {"uv": [5.5, 11.75, 10.25, 13.75], "texture": "#2"},
				"up": {"uv": [6, 0, 9.5, 4.25], "texture": "#2"},
				"down": {"uv": [6.5, 14.25, 10, 16], "texture": "#2"}
			}
		},
		{
			"from": [9.15, 12.6, 6.95],
			"to": [10, 12.95, 7.75],
			"rotation": {"angle": 0, "axis": "y", "origin": [17.1, 17.4, 15]},
			"faces": {
				"north": {"uv": [5.25, 5.25, 10, 7.25], "texture": "#2"},
				"east": {"uv": [5.25, 5.25, 10, 7.25], "texture": "#2"},
				"south": {"uv": [5.25, 5.25, 10, 7.25], "texture": "#2"},
				"west": {"uv": [5.25, 5.25, 10, 7.25], "texture": "#2"},
				"up": {"uv": [6, 0, 9.5, 4.25], "texture": "#2"},
				"down": {"uv": [6.5, 14.25, 10, 16], "texture": "#2"}
			}
		},
		{
			"from": [9.15, 13.1, 6.95],
			"to": [10, 13.45, 7.75],
			"rotation": {"angle": 0, "axis": "y", "origin": [17.1, 17.9, 15]},
			"faces": {
				"north": {"uv": [5.5, 1, 10.25, 3], "texture": "#2"},
				"east": {"uv": [5.5, 1, 10.25, 3], "texture": "#2"},
				"south": {"uv": [5.5, 1, 10.25, 3], "texture": "#2"},
				"west": {"uv": [5.5, 1, 10.25, 3], "texture": "#2"},
				"up": {"uv": [6, 0, 9.5, 4.25], "texture": "#2"},
				"down": {"uv": [6.5, 14.25, 10, 16], "texture": "#2"}
			}
		},
		{
			"from": [9.15, 13.6, 6.95],
			"to": [10, 13.95, 7.75],
			"rotation": {"angle": 0, "axis": "y", "origin": [17.1, 18.4, 15]},
			"faces": {
				"north": {"uv": [5.5, 9.5, 10.25, 11.5], "texture": "#2"},
				"east": {"uv": [5.5, 9.5, 10.25, 11.5], "texture": "#2"},
				"south": {"uv": [5.5, 9.5, 10.25, 11.5], "texture": "#2"},
				"west": {"uv": [5.5, 9.5, 10.25, 11.5], "texture": "#2"},
				"up": {"uv": [6, 0, 9.5, 4.25], "texture": "#2"},
				"down": {"uv": [6.5, 14.25, 10, 16], "texture": "#2"}
			}
		},
		{
			"from": [9.15, 14.1, 6.95],
			"to": [10, 14.45, 7.75],
			"rotation": {"angle": 0, "axis": "y", "origin": [17.1, 18.9, 15]},
			"faces": {
				"north": {"uv": [5.25, 5.25, 10, 7.25], "texture": "#2"},
				"east": {"uv": [5.25, 5.25, 10, 7.25], "texture": "#2"},
				"south": {"uv": [5.25, 5.25, 10, 7.25], "texture": "#2"},
				"west": {"uv": [5.25, 5.25, 10, 7.25], "texture": "#2"},
				"up": {"uv": [6, 0, 9.5, 4.25], "texture": "#2"},
				"down": {"uv": [6.5, 14.25, 10, 16], "texture": "#2"}
			}
		},
		{
			"from": [9.35, 4.95, 7.2],
			"to": [9.75, 11.85, 7.5],
			"rotation": {"angle": 0, "axis": "y", "origin": [17, 8, 14.9]},
			"faces": {
				"north": {"uv": [7.75, 1, 8.5, 15], "texture": "#0"},
				"east": {"uv": [7.75, 1, 8.5, 15], "texture": "#0"},
				"south": {"uv": [7.75, 1, 8.5, 15], "texture": "#0"},
				"west": {"uv": [7.75, 1, 8.5, 15], "texture": "#0"},
				"up": {"uv": [7.75, 1, 8.5, 2.5], "texture": "#0"},
				"down": {"uv": [13, 0, 16, 3.25], "texture": "#0"}
			}
		},
		{
			"from": [9.35, -0.1, 7.2],
			"to": [9.75, 5.1, 7.5],
			"rotation": {"angle": 0, "axis": "y", "origin": [17, 1.25, 14.9]},
			"faces": {
				"north": {"uv": [7.75, 1, 8.5, 15], "texture": "#0"},
				"east": {"uv": [7.75, 1, 8.5, 15], "texture": "#0"},
				"south": {"uv": [7.75, 1, 8.5, 15], "texture": "#0"},
				"west": {"uv": [7.75, 1, 8.5, 15], "texture": "#0"},
				"up": {"uv": [7.75, 1, 8.5, 2.5], "texture": "#0"},
				"down": {"uv": [13, 0, 16, 3.25], "texture": "#0"}
			}
		},
		{
			"from": [9.475, -0.4, 4.525],
			"to": [9.475, 7.4, 9.875],
			"rotation": {"angle": 0, "axis": "y", "origin": [9.475, 1, 7.15]},
			"faces": {
				"north": {"uv": [6, 4, 10.5, 12.75], "texture": "#2"},
				"east": {"uv": [0, 0, 16, 16], "texture": "#4"},
				"south": {"uv": [6, 4, 10.5, 12.75], "texture": "#2"},
				"west": {"uv": [0, 0, 16, 16], "texture": "#3"},
				"up": {"uv": [6, 4, 10.5, 6.75], "rotation": 270, "texture": "#2"},
				"down": {"uv": [13, 0, 16, 3.25], "rotation": 90, "texture": "#0"}
			}
		},
		{
			"from": [9.475, 7.2, 5.025],
			"to": [9.475, 13, 9.375],
			"rotation": {"angle": 0, "axis": "y", "origin": [9.475, 6.6, 7.15]},
			"faces": {
				"north": {"uv": [6, 4, 10.5, 12.75], "texture": "#2"},
				"east": {"uv": [0, 0, 16, 16], "texture": "#4"},
				"south": {"uv": [6, 4, 10.5, 12.75], "texture": "#2"},
				"west": {"uv": [0, 0, 16, 16], "texture": "#3"},
				"up": {"uv": [6, 4, 10.5, 6.75], "rotation": 270, "texture": "#2"},
				"down": {"uv": [13, 0, 16, 3.25], "rotation": 90, "texture": "#0"}
			}
		},
		{
			"from": [6.75, -0.4, 7.45],
			"to": [12.1, 7.4, 7.45],
			"rotation": {"angle": 0, "axis": "y", "origin": [9.575, 3.5, 7.35]},
			"faces": {
				"north": {"uv": [0, 0, 16, 16], "texture": "#4"},
				"east": {"uv": [6, 4, 10.5, 12.75], "texture": "#2"},
				"south": {"uv": [0, 0, 16, 16], "texture": "#3"},
				"west": {"uv": [6, 4, 10.5, 12.75], "texture": "#2"},
				"up": {"uv": [6, 4, 10.5, 6.75], "rotation": 180, "texture": "#2"},
				"down": {"uv": [13, 0, 16, 3.25], "rotation": 180, "texture": "#0"}
			}
		},
		{
			"from": [7.25, 7.1, 7.45],
			"to": [11.6, 13.6, 7.45],
			"rotation": {"angle": 0, "axis": "y", "origin": [9.575, 9.7, 7.35]},
			"faces": {
				"north": {"uv": [0, 0, 16, 16], "texture": "#4"},
				"east": {"uv": [6, 4, 10.5, 12.75], "texture": "#2"},
				"south": {"uv": [0, 0, 16, 16], "texture": "#3"},
				"west": {"uv": [6, 4, 10.5, 12.75], "texture": "#2"},
				"up": {"uv": [6, 4, 10.5, 6.75], "rotation": 180, "texture": "#2"},
				"down": {"uv": [13, 0, 16, 3.25], "rotation": 180, "texture": "#0"}
			}
		},
		{
			"from": [9.675, -0.4, 4.825],
			"to": [9.675, 7.4, 10.175],
			"rotation": {"angle": 0, "axis": "y", "origin": [9.675, 1, 7.55]},
			"faces": {
				"north": {"uv": [6, 4, 10.5, 12.75], "texture": "#2"},
				"east": {"uv": [0, 0, 16, 16], "texture": "#3"},
				"south": {"uv": [6, 4, 10.5, 12.75], "texture": "#2"},
				"west": {"uv": [0, 0, 16, 16], "texture": "#4"},
				"up": {"uv": [10.5, 6.75, 6, 4], "rotation": 270, "texture": "#2"},
				"down": {"uv": [16, 3.25, 13, 0], "rotation": 90, "texture": "#0"}
			}
		},
		{
			"from": [9.675, 7.2, 5.325],
			"to": [9.675, 13, 9.675],
			"rotation": {"angle": 0, "axis": "y", "origin": [9.675, 6.6, 7.55]},
			"faces": {
				"north": {"uv": [6, 4, 10.5, 12.75], "texture": "#2"},
				"east": {"uv": [0, 0, 16, 16], "texture": "#3"},
				"south": {"uv": [6, 4, 10.5, 12.75], "texture": "#2"},
				"west": {"uv": [0, 0, 16, 16], "texture": "#4"},
				"up": {"uv": [10.5, 6.75, 6, 4], "rotation": 270, "texture": "#2"},
				"down": {"uv": [16, 3.25, 13, 0], "rotation": 90, "texture": "#0"}
			}
		},
		{
			"from": [7.05, -0.4, 7.25],
			"to": [12.4, 7.4, 7.25],
			"rotation": {"angle": 0, "axis": "y", "origin": [9.575, 3.5, 7.35]},
			"faces": {
				"north": {"uv": [0, 0, 16, 16], "texture": "#3"},
				"east": {"uv": [6, 4, 10.5, 12.75], "texture": "#2"},
				"south": {"uv": [0, 0, 16, 16], "texture": "#4"},
				"west": {"uv": [6, 4, 10.5, 12.75], "texture": "#2"},
				"up": {"uv": [10.5, 6.75, 6, 4], "rotation": 180, "texture": "#2"},
				"down": {"uv": [16, 3.25, 13, 0], "rotation": 180, "texture": "#0"}
			}
		},
		{
			"from": [7.55, 7.1, 7.25],
			"to": [11.9, 13.6, 7.25],
			"rotation": {"angle": 0, "axis": "y", "origin": [9.575, 9.7, 7.35]},
			"faces": {
				"north": {"uv": [0, 0, 16, 16], "texture": "#3"},
				"east": {"uv": [6, 4, 10.5, 12.75], "texture": "#2"},
				"south": {"uv": [0, 0, 16, 16], "texture": "#4"},
				"west": {"uv": [6, 4, 10.5, 12.75], "texture": "#2"},
				"up": {"uv": [10.5, 6.75, 6, 4], "rotation": 180, "texture": "#2"},
				"down": {"uv": [16, 3.25, 13, 0], "rotation": 180, "texture": "#0"}
			}
		},
		{
			"from": [12.15, 11.8, 3.7],
			"to": [12.8, 12.15, 4.3],
			"rotation": {"angle": 22.5, "axis": "y", "origin": [12.47262, 10.07738, 4]},
			"faces": {
				"north": {"uv": [6.5, 14.25, 10, 16], "texture": "#2"},
				"east": {"uv": [6.5, 14.25, 10, 16], "texture": "#2"},
				"south": {"uv": [6.5, 14.25, 10, 16], "texture": "#2"},
				"west": {"uv": [6.5, 14.25, 10, 16], "texture": "#2"},
				"down": {"uv": [6.5, 14.25, 10, 16], "texture": "#2"}
			}
		},
		{
			"from": [12.15, 12.3, 3.7],
			"to": [12.8, 12.65, 4.3],
			"rotation": {"angle": 22.5, "axis": "y", "origin": [12.47262, 10.07738, 4]},
			"faces": {
				"north": {"uv": [6, 8, 9.5, 9.75], "texture": "#2"},
				"east": {"uv": [6, 8, 9.5, 9.75], "texture": "#2"},
				"south": {"uv": [6, 8, 9.5, 9.75], "texture": "#2"},
				"west": {"uv": [6, 8, 9.5, 9.75], "texture": "#2"}
			}
		},
		{
			"from": [12.15, 12.8, 3.7],
			"to": [12.8, 13.15, 4.3],
			"rotation": {"angle": 22.5, "axis": "y", "origin": [12.47262, 10.07738, 4]},
			"faces": {
				"north": {"uv": [5.5, 3.5, 9, 5.25], "texture": "#2"},
				"east": {"uv": [5.5, 3.5, 9, 5.25], "texture": "#2"},
				"south": {"uv": [5.5, 3.5, 9, 5.25], "texture": "#2"},
				"west": {"uv": [5.5, 3.5, 9, 5.25], "texture": "#2"}
			}
		},
		{
			"from": [12.15, 13.3, 3.7],
			"to": [12.8, 13.65, 4.3],
			"rotation": {"angle": 22.5, "axis": "y", "origin": [12.47262, 10.07738, 4]},
			"faces": {
				"north": {"uv": [5.75, 12.5, 9.25, 14.25], "texture": "#2"},
				"east": {"uv": [5.75, 12.5, 9.25, 14.25], "texture": "#2"},
				"south": {"uv": [5.75, 12.5, 9.25, 14.25], "texture": "#2"},
				"west": {"uv": [5.75, 12.5, 9.25, 14.25], "texture": "#2"}
			}
		},
		{
			"from": [12.15, 13.8, 3.7],
			"to": [12.8, 14.15, 4.3],
			"rotation": {"angle": 22.5, "axis": "y", "origin": [12.47262, 10.07738, 4]},
			"faces": {
				"north": {"uv": [5.75, 4, 9.25, 5.75], "texture": "#2"},
				"east": {"uv": [5.75, 4, 9.25, 5.75], "texture": "#2"},
				"south": {"uv": [5.75, 4, 9.25, 5.75], "texture": "#2"},
				"west": {"uv": [5.75, 4, 9.25, 5.75], "texture": "#2"}
			}
		},
		{
			"from": [12.15, 14.4, 3.7],
			"to": [12.8, 14.75, 4.3],
			"rotation": {"angle": 22.5, "axis": "y", "origin": [12.47262, 10.07738, 4]},
			"faces": {
				"north": {"uv": [5.75, 0, 9.25, 1.75], "texture": "#2"},
				"east": {"uv": [5.75, 0, 9.25, 1.75], "texture": "#2"},
				"south": {"uv": [5.75, 0, 9.25, 1.75], "texture": "#2"},
				"west": {"uv": [5.75, 0, 9.25, 1.75], "texture": "#2"},
				"up": {"uv": [5.75, 0, 9.25, 3], "texture": "#2"}
			}
		},
		{
			"from": [12.05, 12.1, 3.6],
			"to": [12.9, 12.45, 4.4],
			"rotation": {"angle": 22.5, "axis": "y", "origin": [12.47262, 10.07738, 4]},
			"faces": {
				"north": {"uv": [5.5, 11.75, 10.25, 13.75], "texture": "#2"},
				"east": {"uv": [5.5, 11.75, 10.25, 13.75], "texture": "#2"},
				"south": {"uv": [5.5, 11.75, 10.25, 13.75], "texture": "#2"},
				"west": {"uv": [5.5, 11.75, 10.25, 13.75], "texture": "#2"},
				"up": {"uv": [6, 0, 9.5, 4.25], "texture": "#2"},
				"down": {"uv": [6.5, 14.25, 10, 16], "texture": "#2"}
			}
		},
		{
			"from": [12.05, 12.6, 3.6],
			"to": [12.9, 12.95, 4.4],
			"rotation": {"angle": 22.5, "axis": "y", "origin": [12.47262, 10.07738, 4]},
			"faces": {
				"north": {"uv": [5.25, 5.25, 10, 7.25], "texture": "#2"},
				"east": {"uv": [5.25, 5.25, 10, 7.25], "texture": "#2"},
				"south": {"uv": [5.25, 5.25, 10, 7.25], "texture": "#2"},
				"west": {"uv": [5.25, 5.25, 10, 7.25], "texture": "#2"},
				"up": {"uv": [6, 0, 9.5, 4.25], "texture": "#2"},
				"down": {"uv": [6.5, 14.25, 10, 16], "texture": "#2"}
			}
		},
		{
			"from": [12.05, 13.1, 3.6],
			"to": [12.9, 13.45, 4.4],
			"rotation": {"angle": 22.5, "axis": "y", "origin": [12.47262, 10.07738, 4]},
			"faces": {
				"north": {"uv": [5.5, 1, 10.25, 3], "texture": "#2"},
				"east": {"uv": [5.5, 1, 10.25, 3], "texture": "#2"},
				"south": {"uv": [5.5, 1, 10.25, 3], "texture": "#2"},
				"west": {"uv": [5.5, 1, 10.25, 3], "texture": "#2"},
				"up": {"uv": [6, 0, 9.5, 4.25], "texture": "#2"},
				"down": {"uv": [6.5, 14.25, 10, 16], "texture": "#2"}
			}
		},
		{
			"from": [12.05, 13.6, 3.6],
			"to": [12.9, 13.95, 4.4],
			"rotation": {"angle": 22.5, "axis": "y", "origin": [12.47262, 10.07738, 4]},
			"faces": {
				"north": {"uv": [5.5, 9.5, 10.25, 11.5], "texture": "#2"},
				"east": {"uv": [5.5, 9.5, 10.25, 11.5], "texture": "#2"},
				"south": {"uv": [5.5, 9.5, 10.25, 11.5], "texture": "#2"},
				"west": {"uv": [5.5, 9.5, 10.25, 11.5], "texture": "#2"},
				"up": {"uv": [6, 0, 9.5, 4.25], "texture": "#2"},
				"down": {"uv": [6.5, 14.25, 10, 16], "texture": "#2"}
			}
		},
		{
			"from": [12.05, 14.1, 3.6],
			"to": [12.9, 14.45, 4.4],
			"rotation": {"angle": 22.5, "axis": "y", "origin": [12.47262, 10.07738, 4]},
			"faces": {
				"north": {"uv": [5.25, 5.25, 10, 7.25], "texture": "#2"},
				"east": {"uv": [5.25, 5.25, 10, 7.25], "texture": "#2"},
				"south": {"uv": [5.25, 5.25, 10, 7.25], "texture": "#2"},
				"west": {"uv": [5.25, 5.25, 10, 7.25], "texture": "#2"},
				"up": {"uv": [6, 0, 9.5, 4.25], "texture": "#2"},
				"down": {"uv": [6.5, 14.25, 10, 16], "texture": "#2"}
			}
		},
		{
			"from": [12.25, 4.95, 3.85],
			"to": [12.65, 11.85, 4.15],
			"rotation": {"angle": 22.5, "axis": "y", "origin": [12.47262, 10.07738, 4]},
			"faces": {
				"north": {"uv": [7.75, 1, 8.5, 15], "texture": "#0"},
				"east": {"uv": [7.75, 1, 8.5, 15], "texture": "#0"},
				"south": {"uv": [7.75, 1, 8.5, 15], "texture": "#0"},
				"west": {"uv": [7.75, 1, 8.5, 15], "texture": "#0"},
				"up": {"uv": [7.75, 1, 8.5, 2.5], "texture": "#0"},
				"down": {"uv": [13, 0, 16, 3.25], "texture": "#0"}
			}
		},
		{
			"from": [12.25, -0.1, 3.85],
			"to": [12.65, 5.1, 4.15],
			"rotation": {"angle": 22.5, "axis": "y", "origin": [12.47262, 10.07738, 4]},
			"faces": {
				"north": {"uv": [7.75, 1, 8.5, 15], "texture": "#0"},
				"east": {"uv": [7.75, 1, 8.5, 15], "texture": "#0"},
				"south": {"uv": [7.75, 1, 8.5, 15], "texture": "#0"},
				"west": {"uv": [7.75, 1, 8.5, 15], "texture": "#0"},
				"up": {"uv": [7.75, 1, 8.5, 2.5], "texture": "#0"},
				"down": {"uv": [13, 0, 16, 3.25], "texture": "#0"}
			}
		},
		{
			"from": [12.375, -0.4, 1.175],
			"to": [12.375, 7.4, 6.525],
			"rotation": {"angle": 22.5, "axis": "y", "origin": [12.47262, 10.07738, 4]},
			"faces": {
				"north": {"uv": [6, 4, 10.5, 12.75], "texture": "#2"},
				"east": {"uv": [0, 0, 16, 16], "texture": "#4"},
				"south": {"uv": [6, 4, 10.5, 12.75], "texture": "#2"},
				"west": {"uv": [0, 0, 16, 16], "texture": "#3"},
				"up": {"uv": [6, 4, 10.5, 6.75], "rotation": 270, "texture": "#2"},
				"down": {"uv": [13, 0, 16, 3.25], "rotation": 90, "texture": "#0"}
			}
		},
		{
			"from": [12.375, 7.2, 1.675],
			"to": [12.375, 13, 6.025],
			"rotation": {"angle": 22.5, "axis": "y", "origin": [12.47262, 10.07738, 4]},
			"faces": {
				"north": {"uv": [6, 4, 10.5, 12.75], "texture": "#2"},
				"east": {"uv": [0, 0, 16, 16], "texture": "#4"},
				"south": {"uv": [6, 4, 10.5, 12.75], "texture": "#2"},
				"west": {"uv": [0, 0, 16, 16], "texture": "#3"},
				"up": {"uv": [6, 4, 10.5, 6.75], "rotation": 270, "texture": "#2"},
				"down": {"uv": [13, 0, 16, 3.25], "rotation": 90, "texture": "#0"}
			}
		},
		{
			"from": [9.65, -0.4, 4.1],
			"to": [15, 7.4, 4.1],
			"rotation": {"angle": 22.5, "axis": "y", "origin": [12.47262, 10.07738, 4]},
			"faces": {
				"north": {"uv": [0, 0, 16, 16], "texture": "#4"},
				"east": {"uv": [6, 4, 10.5, 12.75], "texture": "#2"},
				"south": {"uv": [0, 0, 16, 16], "texture": "#3"},
				"west": {"uv": [6, 4, 10.5, 12.75], "texture": "#2"},
				"up": {"uv": [6, 4, 10.5, 6.75], "rotation": 180, "texture": "#2"},
				"down": {"uv": [13, 0, 16, 3.25], "rotation": 180, "texture": "#0"}
			}
		},
		{
			"from": [10.15, 7.1, 4.1],
			"to": [14.5, 13.6, 4.1],
			"rotation": {"angle": 22.5, "axis": "y", "origin": [12.47262, 10.07738, 4]},
			"faces": {
				"north": {"uv": [0, 0, 16, 16], "texture": "#4"},
				"east": {"uv": [6, 4, 10.5, 12.75], "texture": "#2"},
				"south": {"uv": [0, 0, 16, 16], "texture": "#3"},
				"west": {"uv": [6, 4, 10.5, 12.75], "texture": "#2"},
				"up": {"uv": [6, 4, 10.5, 6.75], "rotation": 180, "texture": "#2"},
				"down": {"uv": [13, 0, 16, 3.25], "rotation": 180, "texture": "#0"}
			}
		},
		{
			"from": [12.575, -0.4, 1.475],
			"to": [12.575, 7.4, 6.825],
			"rotation": {"angle": 22.5, "axis": "y", "origin": [12.47262, 10.07738, 4]},
			"faces": {
				"north": {"uv": [6, 4, 10.5, 12.75], "texture": "#2"},
				"east": {"uv": [0, 0, 16, 16], "texture": "#3"},
				"south": {"uv": [6, 4, 10.5, 12.75], "texture": "#2"},
				"west": {"uv": [0, 0, 16, 16], "texture": "#4"},
				"up": {"uv": [10.5, 6.75, 6, 4], "rotation": 270, "texture": "#2"},
				"down": {"uv": [16, 3.25, 13, 0], "rotation": 90, "texture": "#0"}
			}
		},
		{
			"from": [12.575, 7.2, 1.975],
			"to": [12.575, 13, 6.325],
			"rotation": {"angle": 22.5, "axis": "y", "origin": [12.47262, 10.07738, 4]},
			"faces": {
				"north": {"uv": [6, 4, 10.5, 12.75], "texture": "#2"},
				"east": {"uv": [0, 0, 16, 16], "texture": "#3"},
				"south": {"uv": [6, 4, 10.5, 12.75], "texture": "#2"},
				"west": {"uv": [0, 0, 16, 16], "texture": "#4"},
				"up": {"uv": [10.5, 6.75, 6, 4], "rotation": 270, "texture": "#2"},
				"down": {"uv": [16, 3.25, 13, 0], "rotation": 90, "texture": "#0"}
			}
		},
		{
			"from": [9.95, -0.4, 3.9],
			"to": [15.3, 7.4, 3.9],
			"rotation": {"angle": 22.5, "axis": "y", "origin": [12.47262, 10.07738, 4]},
			"faces": {
				"north": {"uv": [0, 0, 16, 16], "texture": "#3"},
				"east": {"uv": [6, 4, 10.5, 12.75], "texture": "#2"},
				"south": {"uv": [0, 0, 16, 16], "texture": "#4"},
				"west": {"uv": [6, 4, 10.5, 12.75], "texture": "#2"},
				"up": {"uv": [10.5, 6.75, 6, 4], "rotation": 180, "texture": "#2"},
				"down": {"uv": [16, 3.25, 13, 0], "rotation": 180, "texture": "#0"}
			}
		},
		{
			"from": [10.45, 7.1, 3.9],
			"to": [14.8, 13.6, 3.9],
			"rotation": {"angle": 22.5, "axis": "y", "origin": [12.47262, 10.07738, 4]},
			"faces": {
				"north": {"uv": [0, 0, 16, 16], "texture": "#3"},
				"east": {"uv": [6, 4, 10.5, 12.75], "texture": "#2"},
				"south": {"uv": [0, 0, 16, 16], "texture": "#4"},
				"west": {"uv": [6, 4, 10.5, 12.75], "texture": "#2"},
				"up": {"uv": [10.5, 6.75, 6, 4], "rotation": 180, "texture": "#2"},
				"down": {"uv": [16, 3.25, 13, 0], "rotation": 180, "texture": "#0"}
			}
		},
		{
			"from": [5.75, 11.8, 4.1],
			"to": [6.4, 12.15, 4.7],
			"rotation": {"angle": 0, "axis": "y", "origin": [13.6, 16.6, 12.05]},
			"faces": {
				"north": {"uv": [6.5, 14.25, 10, 16], "texture": "#2"},
				"east": {"uv": [6.5, 14.25, 10, 16], "texture": "#2"},
				"south": {"uv": [6.5, 14.25, 10, 16], "texture": "#2"},
				"west": {"uv": [6.5, 14.25, 10, 16], "texture": "#2"},
				"down": {"uv": [6.5, 14.25, 10, 16], "texture": "#2"}
			}
		},
		{
			"from": [5.75, 12.3, 4.1],
			"to": [6.4, 12.65, 4.7],
			"rotation": {"angle": 0, "axis": "y", "origin": [13.6, 17.1, 12.05]},
			"faces": {
				"north": {"uv": [6, 8, 9.5, 9.75], "texture": "#2"},
				"east": {"uv": [6, 8, 9.5, 9.75], "texture": "#2"},
				"south": {"uv": [6, 8, 9.5, 9.75], "texture": "#2"},
				"west": {"uv": [6, 8, 9.5, 9.75], "texture": "#2"}
			}
		},
		{
			"from": [5.75, 12.8, 4.1],
			"to": [6.4, 13.15, 4.7],
			"rotation": {"angle": 0, "axis": "y", "origin": [13.6, 17.6, 12.05]},
			"faces": {
				"north": {"uv": [5.5, 3.5, 9, 5.25], "texture": "#2"},
				"east": {"uv": [5.5, 3.5, 9, 5.25], "texture": "#2"},
				"south": {"uv": [5.5, 3.5, 9, 5.25], "texture": "#2"},
				"west": {"uv": [5.5, 3.5, 9, 5.25], "texture": "#2"}
			}
		},
		{
			"from": [5.75, 13.3, 4.1],
			"to": [6.4, 13.65, 4.7],
			"rotation": {"angle": 0, "axis": "y", "origin": [13.6, 18.1, 12.05]},
			"faces": {
				"north": {"uv": [5.75, 12.5, 9.25, 14.25], "texture": "#2"},
				"east": {"uv": [5.75, 12.5, 9.25, 14.25], "texture": "#2"},
				"south": {"uv": [5.75, 12.5, 9.25, 14.25], "texture": "#2"},
				"west": {"uv": [5.75, 12.5, 9.25, 14.25], "texture": "#2"}
			}
		},
		{
			"from": [5.75, 13.8, 4.1],
			"to": [6.4, 14.15, 4.7],
			"rotation": {"angle": 0, "axis": "y", "origin": [13.6, 18.6, 12.05]},
			"faces": {
				"north": {"uv": [5.75, 4, 9.25, 5.75], "texture": "#2"},
				"east": {"uv": [5.75, 4, 9.25, 5.75], "texture": "#2"},
				"south": {"uv": [5.75, 4, 9.25, 5.75], "texture": "#2"},
				"west": {"uv": [5.75, 4, 9.25, 5.75], "texture": "#2"}
			}
		},
		{
			"from": [5.75, 14.4, 4.1],
			"to": [6.4, 14.75, 4.7],
			"rotation": {"angle": 0, "axis": "y", "origin": [13.6, 19.2, 12.05]},
			"faces": {
				"north": {"uv": [5.75, 0, 9.25, 1.75], "texture": "#2"},
				"east": {"uv": [5.75, 0, 9.25, 1.75], "texture": "#2"},
				"south": {"uv": [5.75, 0, 9.25, 1.75], "texture": "#2"},
				"west": {"uv": [5.75, 0, 9.25, 1.75], "texture": "#2"},
				"up": {"uv": [5.75, 0, 9.25, 3], "texture": "#2"}
			}
		},
		{
			"from": [5.65, 12.1, 4],
			"to": [6.5, 12.45, 4.8],
			"rotation": {"angle": 0, "axis": "y", "origin": [13.6, 16.9, 12.05]},
			"faces": {
				"north": {"uv": [5.5, 11.75, 10.25, 13.75], "texture": "#2"},
				"east": {"uv": [5.5, 11.75, 10.25, 13.75], "texture": "#2"},
				"south": {"uv": [5.5, 11.75, 10.25, 13.75], "texture": "#2"},
				"west": {"uv": [5.5, 11.75, 10.25, 13.75], "texture": "#2"},
				"up": {"uv": [6, 0, 9.5, 4.25], "texture": "#2"},
				"down": {"uv": [6.5, 14.25, 10, 16], "texture": "#2"}
			}
		},
		{
			"from": [5.65, 12.6, 4],
			"to": [6.5, 12.95, 4.8],
			"rotation": {"angle": 0, "axis": "y", "origin": [13.6, 17.4, 12.05]},
			"faces": {
				"north": {"uv": [5.25, 5.25, 10, 7.25], "texture": "#2"},
				"east": {"uv": [5.25, 5.25, 10, 7.25], "texture": "#2"},
				"south": {"uv": [5.25, 5.25, 10, 7.25], "texture": "#2"},
				"west": {"uv": [5.25, 5.25, 10, 7.25], "texture": "#2"},
				"up": {"uv": [6, 0, 9.5, 4.25], "texture": "#2"},
				"down": {"uv": [6.5, 14.25, 10, 16], "texture": "#2"}
			}
		},
		{
			"from": [5.65, 13.1, 4],
			"to": [6.5, 13.45, 4.8],
			"rotation": {"angle": 0, "axis": "y", "origin": [13.6, 17.9, 12.05]},
			"faces": {
				"north": {"uv": [5.5, 1, 10.25, 3], "texture": "#2"},
				"east": {"uv": [5.5, 1, 10.25, 3], "texture": "#2"},
				"south": {"uv": [5.5, 1, 10.25, 3], "texture": "#2"},
				"west": {"uv": [5.5, 1, 10.25, 3], "texture": "#2"},
				"up": {"uv": [6, 0, 9.5, 4.25], "texture": "#2"},
				"down": {"uv": [6.5, 14.25, 10, 16], "texture": "#2"}
			}
		},
		{
			"from": [5.65, 13.6, 4],
			"to": [6.5, 13.95, 4.8],
			"rotation": {"angle": 0, "axis": "y", "origin": [13.6, 18.4, 12.05]},
			"faces": {
				"north": {"uv": [5.5, 9.5, 10.25, 11.5], "texture": "#2"},
				"east": {"uv": [5.5, 9.5, 10.25, 11.5], "texture": "#2"},
				"south": {"uv": [5.5, 9.5, 10.25, 11.5], "texture": "#2"},
				"west": {"uv": [5.5, 9.5, 10.25, 11.5], "texture": "#2"},
				"up": {"uv": [6, 0, 9.5, 4.25], "texture": "#2"},
				"down": {"uv": [6.5, 14.25, 10, 16], "texture": "#2"}
			}
		},
		{
			"from": [5.65, 14.1, 4],
			"to": [6.5, 14.45, 4.8],
			"rotation": {"angle": 0, "axis": "y", "origin": [13.6, 18.9, 12.05]},
			"faces": {
				"north": {"uv": [5.25, 5.25, 10, 7.25], "texture": "#2"},
				"east": {"uv": [5.25, 5.25, 10, 7.25], "texture": "#2"},
				"south": {"uv": [5.25, 5.25, 10, 7.25], "texture": "#2"},
				"west": {"uv": [5.25, 5.25, 10, 7.25], "texture": "#2"},
				"up": {"uv": [6, 0, 9.5, 4.25], "texture": "#2"},
				"down": {"uv": [6.5, 14.25, 10, 16], "texture": "#2"}
			}
		},
		{
			"from": [5.85, 4.95, 4.25],
			"to": [6.25, 11.85, 4.55],
			"rotation": {"angle": 0, "axis": "y", "origin": [13.5, 8, 11.95]},
			"faces": {
				"north": {"uv": [7.75, 1, 8.5, 15], "texture": "#0"},
				"east": {"uv": [7.75, 1, 8.5, 15], "texture": "#0"},
				"south": {"uv": [7.75, 1, 8.5, 15], "texture": "#0"},
				"west": {"uv": [7.75, 1, 8.5, 15], "texture": "#0"},
				"up": {"uv": [7.75, 1, 8.5, 2.5], "texture": "#0"},
				"down": {"uv": [13, 0, 16, 3.25], "texture": "#0"}
			}
		},
		{
			"from": [5.85, -0.1, 4.25],
			"to": [6.25, 5.1, 4.55],
			"rotation": {"angle": 0, "axis": "y", "origin": [13.5, 1.25, 11.95]},
			"faces": {
				"north": {"uv": [7.75, 1, 8.5, 15], "texture": "#0"},
				"east": {"uv": [7.75, 1, 8.5, 15], "texture": "#0"},
				"south": {"uv": [7.75, 1, 8.5, 15], "texture": "#0"},
				"west": {"uv": [7.75, 1, 8.5, 15], "texture": "#0"},
				"up": {"uv": [7.75, 1, 8.5, 2.5], "texture": "#0"},
				"down": {"uv": [13, 0, 16, 3.25], "texture": "#0"}
			}
		},
		{
			"from": [5.975, -0.4, 1.575],
			"to": [5.975, 7.4, 6.925],
			"rotation": {"angle": 0, "axis": "y", "origin": [5.975, 1, 4.2]},
			"faces": {
				"north": {"uv": [6, 4, 10.5, 12.75], "texture": "#2"},
				"east": {"uv": [0, 0, 16, 16], "texture": "#4"},
				"south": {"uv": [6, 4, 10.5, 12.75], "texture": "#2"},
				"west": {"uv": [0, 0, 16, 16], "texture": "#3"},
				"up": {"uv": [6, 4, 10.5, 6.75], "rotation": 270, "texture": "#2"},
				"down": {"uv": [13, 0, 16, 3.25], "rotation": 90, "texture": "#0"}
			}
		},
		{
			"from": [5.975, 7.2, 2.075],
			"to": [5.975, 13, 6.425],
			"rotation": {"angle": 0, "axis": "y", "origin": [5.975, 6.6, 4.2]},
			"faces": {
				"north": {"uv": [6, 4, 10.5, 12.75], "texture": "#2"},
				"east": {"uv": [0, 0, 16, 16], "texture": "#4"},
				"south": {"uv": [6, 4, 10.5, 12.75], "texture": "#2"},
				"west": {"uv": [0, 0, 16, 16], "texture": "#3"},
				"up": {"uv": [6, 4, 10.5, 6.75], "rotation": 270, "texture": "#2"},
				"down": {"uv": [13, 0, 16, 3.25], "rotation": 90, "texture": "#0"}
			}
		},
		{
			"from": [3.25, -0.4, 4.5],
			"to": [8.6, 7.4, 4.5],
			"rotation": {"angle": 0, "axis": "y", "origin": [6.075, 3.5, 4.4]},
			"faces": {
				"north": {"uv": [0, 0, 16, 16], "texture": "#4"},
				"east": {"uv": [6, 4, 10.5, 12.75], "texture": "#2"},
				"south": {"uv": [0, 0, 16, 16], "texture": "#3"},
				"west": {"uv": [6, 4, 10.5, 12.75], "texture": "#2"},
				"up": {"uv": [6, 4, 10.5, 6.75], "rotation": 180, "texture": "#2"},
				"down": {"uv": [13, 0, 16, 3.25], "rotation": 180, "texture": "#0"}
			}
		},
		{
			"from": [3.75, 7.1, 4.5],
			"to": [8.1, 13.6, 4.5],
			"rotation": {"angle": 0, "axis": "y", "origin": [6.075, 9.7, 4.4]},
			"faces": {
				"north": {"uv": [0, 0, 16, 16], "texture": "#4"},
				"east": {"uv": [6, 4, 10.5, 12.75], "texture": "#2"},
				"south": {"uv": [0, 0, 16, 16], "texture": "#3"},
				"west": {"uv": [6, 4, 10.5, 12.75], "texture": "#2"},
				"up": {"uv": [6, 4, 10.5, 6.75], "rotation": 180, "texture": "#2"},
				"down": {"uv": [13, 0, 16, 3.25], "rotation": 180, "texture": "#0"}
			}
		},
		{
			"from": [6.175, -0.4, 1.875],
			"to": [6.175, 7.4, 7.225],
			"rotation": {"angle": 0, "axis": "y", "origin": [6.175, 1, 4.6]},
			"faces": {
				"north": {"uv": [6, 4, 10.5, 12.75], "texture": "#2"},
				"east": {"uv": [0, 0, 16, 16], "texture": "#3"},
				"south": {"uv": [6, 4, 10.5, 12.75], "texture": "#2"},
				"west": {"uv": [0, 0, 16, 16], "texture": "#4"},
				"up": {"uv": [10.5, 6.75, 6, 4], "rotation": 270, "texture": "#2"},
				"down": {"uv": [16, 3.25, 13, 0], "rotation": 90, "texture": "#0"}
			}
		},
		{
			"from": [6.175, 7.2, 2.375],
			"to": [6.175, 13, 6.725],
			"rotation": {"angle": 0, "axis": "y", "origin": [6.175, 6.6, 4.6]},
			"faces": {
				"north": {"uv": [6, 4, 10.5, 12.75], "texture": "#2"},
				"east": {"uv": [0, 0, 16, 16], "texture": "#3"},
				"south": {"uv": [6, 4, 10.5, 12.75], "texture": "#2"},
				"west": {"uv": [0, 0, 16, 16], "texture": "#4"},
				"up": {"uv": [10.5, 6.75, 6, 4], "rotation": 270, "texture": "#2"},
				"down": {"uv": [16, 3.25, 13, 0], "rotation": 90, "texture": "#0"}
			}
		},
		{
			"from": [3.55, -0.4, 4.3],
			"to": [8.9, 7.4, 4.3],
			"rotation": {"angle": 0, "axis": "y", "origin": [6.075, 3.5, 4.4]},
			"faces": {
				"north": {"uv": [0, 0, 16, 16], "texture": "#3"},
				"east": {"uv": [6, 4, 10.5, 12.75], "texture": "#2"},
				"south": {"uv": [0, 0, 16, 16], "texture": "#4"},
				"west": {"uv": [6, 4, 10.5, 12.75], "texture": "#2"},
				"up": {"uv": [10.5, 6.75, 6, 4], "rotation": 180, "texture": "#2"},
				"down": {"uv": [16, 3.25, 13, 0], "rotation": 180, "texture": "#0"}
			}
		},
		{
			"from": [4.05, 7.1, 4.3],
			"to": [8.4, 13.6, 4.3],
			"rotation": {"angle": 0, "axis": "y", "origin": [6.075, 9.7, 4.4]},
			"faces": {
				"north": {"uv": [0, 0, 16, 16], "texture": "#3"},
				"east": {"uv": [6, 4, 10.5, 12.75], "texture": "#2"},
				"south": {"uv": [0, 0, 16, 16], "texture": "#4"},
				"west": {"uv": [6, 4, 10.5, 12.75], "texture": "#2"},
				"up": {"uv": [10.5, 6.75, 6, 4], "rotation": 180, "texture": "#2"},
				"down": {"uv": [16, 3.25, 13, 0], "rotation": 180, "texture": "#0"}
			}
		},
		{
			"from": [6.25, 11.8, 9.05],
			"to": [6.9, 12.15, 9.65],
			"rotation": {"angle": 0, "axis": "y", "origin": [14.1, 16.6, 17]},
			"faces": {
				"north": {"uv": [6.5, 14.25, 10, 16], "texture": "#2"},
				"east": {"uv": [6.5, 14.25, 10, 16], "texture": "#2"},
				"south": {"uv": [6.5, 14.25, 10, 16], "texture": "#2"},
				"west": {"uv": [6.5, 14.25, 10, 16], "texture": "#2"},
				"down": {"uv": [6.5, 14.25, 10, 16], "texture": "#2"}
			}
		},
		{
			"from": [6.25, 12.3, 9.05],
			"to": [6.9, 12.65, 9.65],
			"rotation": {"angle": 0, "axis": "y", "origin": [14.1, 17.1, 17]},
			"faces": {
				"north": {"uv": [6, 8, 9.5, 9.75], "texture": "#2"},
				"east": {"uv": [6, 8, 9.5, 9.75], "texture": "#2"},
				"south": {"uv": [6, 8, 9.5, 9.75], "texture": "#2"},
				"west": {"uv": [6, 8, 9.5, 9.75], "texture": "#2"}
			}
		},
		{
			"from": [6.25, 12.8, 9.05],
			"to": [6.9, 13.15, 9.65],
			"rotation": {"angle": 0, "axis": "y", "origin": [14.1, 17.6, 17]},
			"faces": {
				"north": {"uv": [5.5, 3.5, 9, 5.25], "texture": "#2"},
				"east": {"uv": [5.5, 3.5, 9, 5.25], "texture": "#2"},
				"south": {"uv": [5.5, 3.5, 9, 5.25], "texture": "#2"},
				"west": {"uv": [5.5, 3.5, 9, 5.25], "texture": "#2"}
			}
		},
		{
			"from": [6.25, 13.3, 9.05],
			"to": [6.9, 13.65, 9.65],
			"rotation": {"angle": 0, "axis": "y", "origin": [14.1, 18.1, 17]},
			"faces": {
				"north": {"uv": [5.75, 12.5, 9.25, 14.25], "texture": "#2"},
				"east": {"uv": [5.75, 12.5, 9.25, 14.25], "texture": "#2"},
				"south": {"uv": [5.75, 12.5, 9.25, 14.25], "texture": "#2"},
				"west": {"uv": [5.75, 12.5, 9.25, 14.25], "texture": "#2"}
			}
		},
		{
			"from": [6.25, 13.8, 9.05],
			"to": [6.9, 14.15, 9.65],
			"rotation": {"angle": 0, "axis": "y", "origin": [14.1, 18.6, 17]},
			"faces": {
				"north": {"uv": [5.75, 4, 9.25, 5.75], "texture": "#2"},
				"east": {"uv": [5.75, 4, 9.25, 5.75], "texture": "#2"},
				"south": {"uv": [5.75, 4, 9.25, 5.75], "texture": "#2"},
				"west": {"uv": [5.75, 4, 9.25, 5.75], "texture": "#2"}
			}
		},
		{
			"from": [6.25, 14.4, 9.05],
			"to": [6.9, 14.75, 9.65],
			"rotation": {"angle": 0, "axis": "y", "origin": [14.1, 19.2, 17]},
			"faces": {
				"north": {"uv": [5.75, 0, 9.25, 1.75], "texture": "#2"},
				"east": {"uv": [5.75, 0, 9.25, 1.75], "texture": "#2"},
				"south": {"uv": [5.75, 0, 9.25, 1.75], "texture": "#2"},
				"west": {"uv": [5.75, 0, 9.25, 1.75], "texture": "#2"},
				"up": {"uv": [5.75, 0, 9.25, 3], "texture": "#2"}
			}
		},
		{
			"from": [6.15, 12.1, 8.95],
			"to": [7, 12.45, 9.75],
			"rotation": {"angle": 0, "axis": "y", "origin": [14.1, 16.9, 17]},
			"faces": {
				"north": {"uv": [5.5, 11.75, 10.25, 13.75], "texture": "#2"},
				"east": {"uv": [5.5, 11.75, 10.25, 13.75], "texture": "#2"},
				"south": {"uv": [5.5, 11.75, 10.25, 13.75], "texture": "#2"},
				"west": {"uv": [5.5, 11.75, 10.25, 13.75], "texture": "#2"},
				"up": {"uv": [6, 0, 9.5, 4.25], "texture": "#2"},
				"down": {"uv": [6.5, 14.25, 10, 16], "texture": "#2"}
			}
		},
		{
			"from": [6.15, 12.6, 8.95],
			"to": [7, 12.95, 9.75],
			"rotation": {"angle": 0, "axis": "y", "origin": [14.1, 17.4, 17]},
			"faces": {
				"north": {"uv": [5.25, 5.25, 10, 7.25], "texture": "#2"},
				"east": {"uv": [5.25, 5.25, 10, 7.25], "texture": "#2"},
				"south": {"uv": [5.25, 5.25, 10, 7.25], "texture": "#2"},
				"west": {"uv": [5.25, 5.25, 10, 7.25], "texture": "#2"},
				"up": {"uv": [6, 0, 9.5, 4.25], "texture": "#2"},
				"down": {"uv": [6.5, 14.25, 10, 16], "texture": "#2"}
			}
		},
		{
			"from": [6.15, 13.1, 8.95],
			"to": [7, 13.45, 9.75],
			"rotation": {"angle": 0, "axis": "y", "origin": [14.1, 17.9, 17]},
			"faces": {
				"north": {"uv": [5.5, 1, 10.25, 3], "texture": "#2"},
				"east": {"uv": [5.5, 1, 10.25, 3], "texture": "#2"},
				"south": {"uv": [5.5, 1, 10.25, 3], "texture": "#2"},
				"west": {"uv": [5.5, 1, 10.25, 3], "texture": "#2"},
				"up": {"uv": [6, 0, 9.5, 4.25], "texture": "#2"},
				"down": {"uv": [6.5, 14.25, 10, 16], "texture": "#2"}
			}
		},
		{
			"from": [6.15, 13.6, 8.95],
			"to": [7, 13.95, 9.75],
			"rotation": {"angle": 0, "axis": "y", "origin": [14.1, 18.4, 17]},
			"faces": {
				"north": {"uv": [5.5, 9.5, 10.25, 11.5], "texture": "#2"},
				"east": {"uv": [5.5, 9.5, 10.25, 11.5], "texture": "#2"},
				"south": {"uv": [5.5, 9.5, 10.25, 11.5], "texture": "#2"},
				"west": {"uv": [5.5, 9.5, 10.25, 11.5], "texture": "#2"},
				"up": {"uv": [6, 0, 9.5, 4.25], "texture": "#2"},
				"down": {"uv": [6.5, 14.25, 10, 16], "texture": "#2"}
			}
		},
		{
			"from": [6.15, 14.1, 8.95],
			"to": [7, 14.45, 9.75],
			"rotation": {"angle": 0, "axis": "y", "origin": [14.1, 18.9, 17]},
			"faces": {
				"north": {"uv": [5.25, 5.25, 10, 7.25], "texture": "#2"},
				"east": {"uv": [5.25, 5.25, 10, 7.25], "texture": "#2"},
				"south": {"uv": [5.25, 5.25, 10, 7.25], "texture": "#2"},
				"west": {"uv": [5.25, 5.25, 10, 7.25], "texture": "#2"},
				"up": {"uv": [6, 0, 9.5, 4.25], "texture": "#2"},
				"down": {"uv": [6.5, 14.25, 10, 16], "texture": "#2"}
			}
		},
		{
			"from": [6.35, 4.95, 9.2],
			"to": [6.75, 11.85, 9.5],
			"rotation": {"angle": 0, "axis": "y", "origin": [14, 8, 16.9]},
			"faces": {
				"north": {"uv": [7.75, 1, 8.5, 15], "texture": "#0"},
				"east": {"uv": [7.75, 1, 8.5, 15], "texture": "#0"},
				"south": {"uv": [7.75, 1, 8.5, 15], "texture": "#0"},
				"west": {"uv": [7.75, 1, 8.5, 15], "texture": "#0"},
				"up": {"uv": [7.75, 1, 8.5, 2.5], "texture": "#0"},
				"down": {"uv": [13, 0, 16, 3.25], "texture": "#0"}
			}
		},
		{
			"from": [6.35, -0.1, 9.2],
			"to": [6.75, 5.1, 9.5],
			"rotation": {"angle": 0, "axis": "y", "origin": [14, 1.25, 16.9]},
			"faces": {
				"north": {"uv": [7.75, 1, 8.5, 15], "texture": "#0"},
				"east": {"uv": [7.75, 1, 8.5, 15], "texture": "#0"},
				"south": {"uv": [7.75, 1, 8.5, 15], "texture": "#0"},
				"west": {"uv": [7.75, 1, 8.5, 15], "texture": "#0"},
				"up": {"uv": [7.75, 1, 8.5, 2.5], "texture": "#0"},
				"down": {"uv": [13, 0, 16, 3.25], "texture": "#0"}
			}
		},
		{
			"from": [6.475, -0.4, 6.525],
			"to": [6.475, 7.4, 11.875],
			"rotation": {"angle": 0, "axis": "y", "origin": [6.475, 1, 9.15]},
			"faces": {
				"north": {"uv": [6, 4, 10.5, 12.75], "texture": "#2"},
				"east": {"uv": [0, 0, 16, 16], "texture": "#4"},
				"south": {"uv": [6, 4, 10.5, 12.75], "texture": "#2"},
				"west": {"uv": [0, 0, 16, 16], "texture": "#3"},
				"up": {"uv": [6, 4, 10.5, 6.75], "rotation": 270, "texture": "#2"},
				"down": {"uv": [13, 0, 16, 3.25], "rotation": 90, "texture": "#0"}
			}
		},
		{
			"from": [6.475, 7.2, 7.025],
			"to": [6.475, 13, 11.375],
			"rotation": {"angle": 0, "axis": "y", "origin": [6.475, 6.6, 9.15]},
			"faces": {
				"north": {"uv": [6, 4, 10.5, 12.75], "texture": "#2"},
				"east": {"uv": [0, 0, 16, 16], "texture": "#4"},
				"south": {"uv": [6, 4, 10.5, 12.75], "texture": "#2"},
				"west": {"uv": [0, 0, 16, 16], "texture": "#3"},
				"up": {"uv": [6, 4, 10.5, 6.75], "rotation": 270, "texture": "#2"},
				"down": {"uv": [13, 0, 16, 3.25], "rotation": 90, "texture": "#0"}
			}
		},
		{
			"from": [3.75, -0.4, 9.45],
			"to": [9.1, 7.4, 9.45],
			"rotation": {"angle": 0, "axis": "y", "origin": [6.575, 3.5, 9.35]},
			"faces": {
				"north": {"uv": [0, 0, 16, 16], "texture": "#4"},
				"east": {"uv": [6, 4, 10.5, 12.75], "texture": "#2"},
				"south": {"uv": [0, 0, 16, 16], "texture": "#3"},
				"west": {"uv": [6, 4, 10.5, 12.75], "texture": "#2"},
				"up": {"uv": [6, 4, 10.5, 6.75], "rotation": 180, "texture": "#2"},
				"down": {"uv": [13, 0, 16, 3.25], "rotation": 180, "texture": "#0"}
			}
		},
		{
			"from": [4.25, 7.1, 9.45],
			"to": [8.6, 13.6, 9.45],
			"rotation": {"angle": 0, "axis": "y", "origin": [6.575, 9.7, 9.35]},
			"faces": {
				"north": {"uv": [0, 0, 16, 16], "texture": "#4"},
				"east": {"uv": [6, 4, 10.5, 12.75], "texture": "#2"},
				"south": {"uv": [0, 0, 16, 16], "texture": "#3"},
				"west": {"uv": [6, 4, 10.5, 12.75], "texture": "#2"},
				"up": {"uv": [6, 4, 10.5, 6.75], "rotation": 180, "texture": "#2"},
				"down": {"uv": [13, 0, 16, 3.25], "rotation": 180, "texture": "#0"}
			}
		},
		{
			"from": [6.675, -0.4, 6.825],
			"to": [6.675, 7.4, 12.175],
			"rotation": {"angle": 0, "axis": "y", "origin": [6.675, 1, 9.55]},
			"faces": {
				"north": {"uv": [6, 4, 10.5, 12.75], "texture": "#2"},
				"east": {"uv": [0, 0, 16, 16], "texture": "#3"},
				"south": {"uv": [6, 4, 10.5, 12.75], "texture": "#2"},
				"west": {"uv": [0, 0, 16, 16], "texture": "#4"},
				"up": {"uv": [10.5, 6.75, 6, 4], "rotation": 270, "texture": "#2"},
				"down": {"uv": [16, 3.25, 13, 0], "rotation": 90, "texture": "#0"}
			}
		},
		{
			"from": [6.675, 7.2, 7.325],
			"to": [6.675, 13, 11.675],
			"rotation": {"angle": 0, "axis": "y", "origin": [6.675, 6.6, 9.55]},
			"faces": {
				"north": {"uv": [6, 4, 10.5, 12.75], "texture": "#2"},
				"east": {"uv": [0, 0, 16, 16], "texture": "#3"},
				"south": {"uv": [6, 4, 10.5, 12.75], "texture": "#2"},
				"west": {"uv": [0, 0, 16, 16], "texture": "#4"},
				"up": {"uv": [10.5, 6.75, 6, 4], "rotation": 270, "texture": "#2"},
				"down": {"uv": [16, 3.25, 13, 0], "rotation": 90, "texture": "#0"}
			}
		},
		{
			"from": [4.05, -0.4, 9.25],
			"to": [9.4, 7.4, 9.25],
			"rotation": {"angle": 0, "axis": "y", "origin": [6.575, 3.5, 9.35]},
			"faces": {
				"north": {"uv": [0, 0, 16, 16], "texture": "#3"},
				"east": {"uv": [6, 4, 10.5, 12.75], "texture": "#2"},
				"south": {"uv": [0, 0, 16, 16], "texture": "#4"},
				"west": {"uv": [6, 4, 10.5, 12.75], "texture": "#2"},
				"up": {"uv": [10.5, 6.75, 6, 4], "rotation": 180, "texture": "#2"},
				"down": {"uv": [16, 3.25, 13, 0], "rotation": 180, "texture": "#0"}
			}
		},
		{
			"from": [4.55, 7.1, 9.25],
			"to": [8.9, 13.6, 9.25],
			"rotation": {"angle": 0, "axis": "y", "origin": [6.575, 9.7, 9.35]},
			"faces": {
				"north": {"uv": [0, 0, 16, 16], "texture": "#3"},
				"east": {"uv": [6, 4, 10.5, 12.75], "texture": "#2"},
				"south": {"uv": [0, 0, 16, 16], "texture": "#4"},
				"west": {"uv": [6, 4, 10.5, 12.75], "texture": "#2"},
				"up": {"uv": [10.5, 6.75, 6, 4], "rotation": 180, "texture": "#2"},
				"down": {"uv": [16, 3.25, 13, 0], "rotation": 180, "texture": "#0"}
			}
		},
		{
			"from": [13, 11.8, 8.25],
			"to": [13.65, 12.15, 8.85],
			"rotation": {"angle": 0, "axis": "y", "origin": [20.85, 16.6, 16.2]},
			"faces": {
				"north": {"uv": [6.5, 14.25, 10, 16], "texture": "#2"},
				"east": {"uv": [6.5, 14.25, 10, 16], "texture": "#2"},
				"south": {"uv": [6.5, 14.25, 10, 16], "texture": "#2"},
				"west": {"uv": [6.5, 14.25, 10, 16], "texture": "#2"},
				"down": {"uv": [6.5, 14.25, 10, 16], "texture": "#2"}
			}
		},
		{
			"from": [13, 12.3, 8.25],
			"to": [13.65, 12.65, 8.85],
			"rotation": {"angle": 0, "axis": "y", "origin": [20.85, 17.1, 16.2]},
			"faces": {
				"north": {"uv": [6, 8, 9.5, 9.75], "texture": "#2"},
				"east": {"uv": [6, 8, 9.5, 9.75], "texture": "#2"},
				"south": {"uv": [6, 8, 9.5, 9.75], "texture": "#2"},
				"west": {"uv": [6, 8, 9.5, 9.75], "texture": "#2"}
			}
		},
		{
			"from": [13, 12.8, 8.25],
			"to": [13.65, 13.15, 8.85],
			"rotation": {"angle": 0, "axis": "y", "origin": [20.85, 17.6, 16.2]},
			"faces": {
				"north": {"uv": [5.5, 3.5, 9, 5.25], "texture": "#2"},
				"east": {"uv": [5.5, 3.5, 9, 5.25], "texture": "#2"},
				"south": {"uv": [5.5, 3.5, 9, 5.25], "texture": "#2"},
				"west": {"uv": [5.5, 3.5, 9, 5.25], "texture": "#2"}
			}
		},
		{
			"from": [13, 13.3, 8.25],
			"to": [13.65, 13.65, 8.85],
			"rotation": {"angle": 0, "axis": "y", "origin": [20.85, 18.1, 16.2]},
			"faces": {
				"north": {"uv": [5.75, 12.5, 9.25, 14.25], "texture": "#2"},
				"east": {"uv": [5.75, 12.5, 9.25, 14.25], "texture": "#2"},
				"south": {"uv": [5.75, 12.5, 9.25, 14.25], "texture": "#2"},
				"west": {"uv": [5.75, 12.5, 9.25, 14.25], "texture": "#2"}
			}
		},
		{
			"from": [13, 13.8, 8.25],
			"to": [13.65, 14.15, 8.85],
			"rotation": {"angle": 0, "axis": "y", "origin": [20.85, 18.6, 16.2]},
			"faces": {
				"north": {"uv": [5.75, 4, 9.25, 5.75], "texture": "#2"},
				"east": {"uv": [5.75, 4, 9.25, 5.75], "texture": "#2"},
				"south": {"uv": [5.75, 4, 9.25, 5.75], "texture": "#2"},
				"west": {"uv": [5.75, 4, 9.25, 5.75], "texture": "#2"}
			}
		},
		{
			"from": [13, 14.4, 8.25],
			"to": [13.65, 14.75, 8.85],
			"rotation": {"angle": 0, "axis": "y", "origin": [20.85, 19.2, 16.2]},
			"faces": {
				"north": {"uv": [5.75, 0, 9.25, 1.75], "texture": "#2"},
				"east": {"uv": [5.75, 0, 9.25, 1.75], "texture": "#2"},
				"south": {"uv": [5.75, 0, 9.25, 1.75], "texture": "#2"},
				"west": {"uv": [5.75, 0, 9.25, 1.75], "texture": "#2"},
				"up": {"uv": [5.75, 0, 9.25, 3], "texture": "#2"}
			}
		},
		{
			"from": [12.9, 12.1, 8.15],
			"to": [13.75, 12.45, 8.95],
			"rotation": {"angle": 0, "axis": "y", "origin": [20.85, 16.9, 16.2]},
			"faces": {
				"north": {"uv": [5.5, 11.75, 10.25, 13.75], "texture": "#2"},
				"east": {"uv": [5.5, 11.75, 10.25, 13.75], "texture": "#2"},
				"south": {"uv": [5.5, 11.75, 10.25, 13.75], "texture": "#2"},
				"west": {"uv": [5.5, 11.75, 10.25, 13.75], "texture": "#2"},
				"up": {"uv": [6, 0, 9.5, 4.25], "texture": "#2"},
				"down": {"uv": [6.5, 14.25, 10, 16], "texture": "#2"}
			}
		},
		{
			"from": [12.9, 12.6, 8.15],
			"to": [13.75, 12.95, 8.95],
			"rotation": {"angle": 0, "axis": "y", "origin": [20.85, 17.4, 16.2]},
			"faces": {
				"north": {"uv": [5.25, 5.25, 10, 7.25], "texture": "#2"},
				"east": {"uv": [5.25, 5.25, 10, 7.25], "texture": "#2"},
				"south": {"uv": [5.25, 5.25, 10, 7.25], "texture": "#2"},
				"west": {"uv": [5.25, 5.25, 10, 7.25], "texture": "#2"},
				"up": {"uv": [6, 0, 9.5, 4.25], "texture": "#2"},
				"down": {"uv": [6.5, 14.25, 10, 16], "texture": "#2"}
			}
		},
		{
			"from": [12.9, 13.1, 8.15],
			"to": [13.75, 13.45, 8.95],
			"rotation": {"angle": 0, "axis": "y", "origin": [20.85, 17.9, 16.2]},
			"faces": {
				"north": {"uv": [5.5, 1, 10.25, 3], "texture": "#2"},
				"east": {"uv": [5.5, 1, 10.25, 3], "texture": "#2"},
				"south": {"uv": [5.5, 1, 10.25, 3], "texture": "#2"},
				"west": {"uv": [5.5, 1, 10.25, 3], "texture": "#2"},
				"up": {"uv": [6, 0, 9.5, 4.25], "texture": "#2"},
				"down": {"uv": [6.5, 14.25, 10, 16], "texture": "#2"}
			}
		},
		{
			"from": [12.9, 13.6, 8.15],
			"to": [13.75, 13.95, 8.95],
			"rotation": {"angle": 0, "axis": "y", "origin": [20.85, 18.4, 16.2]},
			"faces": {
				"north": {"uv": [5.5, 9.5, 10.25, 11.5], "texture": "#2"},
				"east": {"uv": [5.5, 9.5, 10.25, 11.5], "texture": "#2"},
				"south": {"uv": [5.5, 9.5, 10.25, 11.5], "texture": "#2"},
				"west": {"uv": [5.5, 9.5, 10.25, 11.5], "texture": "#2"},
				"up": {"uv": [6, 0, 9.5, 4.25], "texture": "#2"},
				"down": {"uv": [6.5, 14.25, 10, 16], "texture": "#2"}
			}
		},
		{
			"from": [12.9, 14.1, 8.15],
			"to": [13.75, 14.45, 8.95],
			"rotation": {"angle": 0, "axis": "y", "origin": [20.85, 18.9, 16.2]},
			"faces": {
				"north": {"uv": [5.25, 5.25, 10, 7.25], "texture": "#2"},
				"east": {"uv": [5.25, 5.25, 10, 7.25], "texture": "#2"},
				"south": {"uv": [5.25, 5.25, 10, 7.25], "texture": "#2"},
				"west": {"uv": [5.25, 5.25, 10, 7.25], "texture": "#2"},
				"up": {"uv": [6, 0, 9.5, 4.25], "texture": "#2"},
				"down": {"uv": [6.5, 14.25, 10, 16], "texture": "#2"}
			}
		},
		{
			"from": [13.1, 4.95, 8.4],
			"to": [13.5, 11.85, 8.7],
			"rotation": {"angle": 0, "axis": "y", "origin": [20.75, 8, 16.1]},
			"faces": {
				"north": {"uv": [7.75, 1, 8.5, 15], "texture": "#0"},
				"east": {"uv": [7.75, 1, 8.5, 15], "texture": "#0"},
				"south": {"uv": [7.75, 1, 8.5, 15], "texture": "#0"},
				"west": {"uv": [7.75, 1, 8.5, 15], "texture": "#0"},
				"up": {"uv": [7.75, 1, 8.5, 2.5], "texture": "#0"},
				"down": {"uv": [13, 0, 16, 3.25], "texture": "#0"}
			}
		},
		{
			"from": [13.1, -0.1, 8.4],
			"to": [13.5, 5.1, 8.7],
			"rotation": {"angle": 0, "axis": "y", "origin": [20.75, 1.25, 16.1]},
			"faces": {
				"north": {"uv": [7.75, 1, 8.5, 15], "texture": "#0"},
				"east": {"uv": [7.75, 1, 8.5, 15], "texture": "#0"},
				"south": {"uv": [7.75, 1, 8.5, 15], "texture": "#0"},
				"west": {"uv": [7.75, 1, 8.5, 15], "texture": "#0"},
				"up": {"uv": [7.75, 1, 8.5, 2.5], "texture": "#0"},
				"down": {"uv": [13, 0, 16, 3.25], "texture": "#0"}
			}
		},
		{
			"from": [13.225, -0.4, 5.725],
			"to": [13.225, 7.4, 11.075],
			"rotation": {"angle": 0, "axis": "y", "origin": [13.225, 1, 8.35]},
			"faces": {
				"north": {"uv": [6, 4, 10.5, 12.75], "texture": "#2"},
				"east": {"uv": [0, 0, 16, 16], "texture": "#4"},
				"south": {"uv": [6, 4, 10.5, 12.75], "texture": "#2"},
				"west": {"uv": [0, 0, 16, 16], "texture": "#3"},
				"up": {"uv": [6, 4, 10.5, 6.75], "rotation": 270, "texture": "#2"},
				"down": {"uv": [13, 0, 16, 3.25], "rotation": 90, "texture": "#0"}
			}
		},
		{
			"from": [13.225, 7.2, 6.225],
			"to": [13.225, 13, 10.575],
			"rotation": {"angle": 0, "axis": "y", "origin": [13.225, 6.6, 8.35]},
			"faces": {
				"north": {"uv": [6, 4, 10.5, 12.75], "texture": "#2"},
				"east": {"uv": [0, 0, 16, 16], "texture": "#4"},
				"south": {"uv": [6, 4, 10.5, 12.75], "texture": "#2"},
				"west": {"uv": [0, 0, 16, 16], "texture": "#3"},
				"up": {"uv": [6, 4, 10.5, 6.75], "rotation": 270, "texture": "#2"},
				"down": {"uv": [13, 0, 16, 3.25], "rotation": 90, "texture": "#0"}
			}
		},
		{
			"from": [10.5, -0.4, 8.65],
			"to": [15.85, 7.4, 8.65],
			"rotation": {"angle": 0, "axis": "y", "origin": [13.325, 3.5, 8.55]},
			"faces": {
				"north": {"uv": [0, 0, 16, 16], "texture": "#4"},
				"east": {"uv": [6, 4, 10.5, 12.75], "texture": "#2"},
				"south": {"uv": [0, 0, 16, 16], "texture": "#3"},
				"west": {"uv": [6, 4, 10.5, 12.75], "texture": "#2"},
				"up": {"uv": [6, 4, 10.5, 6.75], "rotation": 180, "texture": "#2"},
				"down": {"uv": [13, 0, 16, 3.25], "rotation": 180, "texture": "#0"}
			}
		},
		{
			"from": [11, 7.1, 8.65],
			"to": [15.35, 13.6, 8.65],
			"rotation": {"angle": 0, "axis": "y", "origin": [13.325, 9.7, 8.55]},
			"faces": {
				"north": {"uv": [0, 0, 16, 16], "texture": "#4"},
				"east": {"uv": [6, 4, 10.5, 12.75], "texture": "#2"},
				"south": {"uv": [0, 0, 16, 16], "texture": "#3"},
				"west": {"uv": [6, 4, 10.5, 12.75], "texture": "#2"},
				"up": {"uv": [6, 4, 10.5, 6.75], "rotation": 180, "texture": "#2"},
				"down": {"uv": [13, 0, 16, 3.25], "rotation": 180, "texture": "#0"}
			}
		},
		{
			"from": [13.425, -0.4, 6.025],
			"to": [13.425, 7.4, 11.375],
			"rotation": {"angle": 0, "axis": "y", "origin": [13.425, 1, 8.75]},
			"faces": {
				"north": {"uv": [6, 4, 10.5, 12.75], "texture": "#2"},
				"east": {"uv": [0, 0, 16, 16], "texture": "#3"},
				"south": {"uv": [6, 4, 10.5, 12.75], "texture": "#2"},
				"west": {"uv": [0, 0, 16, 16], "texture": "#4"},
				"up": {"uv": [10.5, 6.75, 6, 4], "rotation": 270, "texture": "#2"},
				"down": {"uv": [16, 3.25, 13, 0], "rotation": 90, "texture": "#0"}
			}
		},
		{
			"from": [13.425, 7.2, 6.525],
			"to": [13.425, 13, 10.875],
			"rotation": {"angle": 0, "axis": "y", "origin": [13.425, 6.6, 8.75]},
			"faces": {
				"north": {"uv": [6, 4, 10.5, 12.75], "texture": "#2"},
				"east": {"uv": [0, 0, 16, 16], "texture": "#3"},
				"south": {"uv": [6, 4, 10.5, 12.75], "texture": "#2"},
				"west": {"uv": [0, 0, 16, 16], "texture": "#4"},
				"up": {"uv": [10.5, 6.75, 6, 4], "rotation": 270, "texture": "#2"},
				"down": {"uv": [16, 3.25, 13, 0], "rotation": 90, "texture": "#0"}
			}
		},
		{
			"from": [10.8, -0.4, 8.45],
			"to": [16.15, 7.4, 8.45],
			"rotation": {"angle": 0, "axis": "y", "origin": [13.325, 3.5, 8.55]},
			"faces": {
				"north": {"uv": [0, 0, 16, 16], "texture": "#3"},
				"east": {"uv": [6, 4, 10.5, 12.75], "texture": "#2"},
				"south": {"uv": [0, 0, 16, 16], "texture": "#4"},
				"west": {"uv": [6, 4, 10.5, 12.75], "texture": "#2"},
				"up": {"uv": [10.5, 6.75, 6, 4], "rotation": 180, "texture": "#2"},
				"down": {"uv": [16, 3.25, 13, 0], "rotation": 180, "texture": "#0"}
			}
		},
		{
			"from": [11.3, 7.1, 8.45],
			"to": [15.65, 13.6, 8.45],
			"rotation": {"angle": 0, "axis": "y", "origin": [13.325, 9.7, 8.55]},
			"faces": {
				"north": {"uv": [0, 0, 16, 16], "texture": "#3"},
				"east": {"uv": [6, 4, 10.5, 12.75], "texture": "#2"},
				"south": {"uv": [0, 0, 16, 16], "texture": "#4"},
				"west": {"uv": [6, 4, 10.5, 12.75], "texture": "#2"},
				"up": {"uv": [10.5, 6.75, 6, 4], "rotation": 180, "texture": "#2"},
				"down": {"uv": [16, 3.25, 13, 0], "rotation": 180, "texture": "#0"}
			}
		},
		{
			"from": [8.5, 11.8, 12.8],
			"to": [9.15, 12.15, 13.4],
			"rotation": {"angle": -45, "axis": "y", "origin": [8.82262, 10.07738, 13.1]},
			"faces": {
				"north": {"uv": [6.5, 14.25, 10, 16], "texture": "#2"},
				"east": {"uv": [6.5, 14.25, 10, 16], "texture": "#2"},
				"south": {"uv": [6.5, 14.25, 10, 16], "texture": "#2"},
				"west": {"uv": [6.5, 14.25, 10, 16], "texture": "#2"},
				"down": {"uv": [6.5, 14.25, 10, 16], "texture": "#2"}
			}
		},
		{
			"from": [8.5, 12.3, 12.8],
			"to": [9.15, 12.65, 13.4],
			"rotation": {"angle": -45, "axis": "y", "origin": [8.82262, 10.07738, 13.1]},
			"faces": {
				"north": {"uv": [6, 8, 9.5, 9.75], "texture": "#2"},
				"east": {"uv": [6, 8, 9.5, 9.75], "texture": "#2"},
				"south": {"uv": [6, 8, 9.5, 9.75], "texture": "#2"},
				"west": {"uv": [6, 8, 9.5, 9.75], "texture": "#2"}
			}
		},
		{
			"from": [8.5, 12.8, 12.8],
			"to": [9.15, 13.15, 13.4],
			"rotation": {"angle": -45, "axis": "y", "origin": [8.82262, 10.07738, 13.1]},
			"faces": {
				"north": {"uv": [5.5, 3.5, 9, 5.25], "texture": "#2"},
				"east": {"uv": [5.5, 3.5, 9, 5.25], "texture": "#2"},
				"south": {"uv": [5.5, 3.5, 9, 5.25], "texture": "#2"},
				"west": {"uv": [5.5, 3.5, 9, 5.25], "texture": "#2"}
			}
		},
		{
			"from": [8.5, 13.3, 12.8],
			"to": [9.15, 13.65, 13.4],
			"rotation": {"angle": -45, "axis": "y", "origin": [8.82262, 10.07738, 13.1]},
			"faces": {
				"north": {"uv": [5.75, 12.5, 9.25, 14.25], "texture": "#2"},
				"east": {"uv": [5.75, 12.5, 9.25, 14.25], "texture": "#2"},
				"south": {"uv": [5.75, 12.5, 9.25, 14.25], "texture": "#2"},
				"west": {"uv": [5.75, 12.5, 9.25, 14.25], "texture": "#2"}
			}
		},
		{
			"from": [8.5, 13.8, 12.8],
			"to": [9.15, 14.15, 13.4],
			"rotation": {"angle": -45, "axis": "y", "origin": [8.82262, 10.07738, 13.1]},
			"faces": {
				"north": {"uv": [5.75, 4, 9.25, 5.75], "texture": "#2"},
				"east": {"uv": [5.75, 4, 9.25, 5.75], "texture": "#2"},
				"south": {"uv": [5.75, 4, 9.25, 5.75], "texture": "#2"},
				"west": {"uv": [5.75, 4, 9.25, 5.75], "texture": "#2"}
			}
		},
		{
			"from": [8.5, 14.4, 12.8],
			"to": [9.15, 14.75, 13.4],
			"rotation": {"angle": -45, "axis": "y", "origin": [8.82262, 10.07738, 13.1]},
			"faces": {
				"north": {"uv": [5.75, 0, 9.25, 1.75], "texture": "#2"},
				"east": {"uv": [5.75, 0, 9.25, 1.75], "texture": "#2"},
				"south": {"uv": [5.75, 0, 9.25, 1.75], "texture": "#2"},
				"west": {"uv": [5.75, 0, 9.25, 1.75], "texture": "#2"},
				"up": {"uv": [5.75, 0, 9.25, 3], "texture": "#2"}
			}
		},
		{
			"from": [8.4, 12.1, 12.7],
			"to": [9.25, 12.45, 13.5],
			"rotation": {"angle": -45, "axis": "y", "origin": [8.82262, 10.07738, 13.1]},
			"faces": {
				"north": {"uv": [5.5, 11.75, 10.25, 13.75], "texture": "#2"},
				"east": {"uv": [5.5, 11.75, 10.25, 13.75], "texture": "#2"},
				"south": {"uv": [5.5, 11.75, 10.25, 13.75], "texture": "#2"},
				"west": {"uv": [5.5, 11.75, 10.25, 13.75], "texture": "#2"},
				"up": {"uv": [6, 0, 9.5, 4.25], "texture": "#2"},
				"down": {"uv": [6.5, 14.25, 10, 16], "texture": "#2"}
			}
		},
		{
			"from": [8.4, 12.6, 12.7],
			"to": [9.25, 12.95, 13.5],
			"rotation": {"angle": -45, "axis": "y", "origin": [8.82262, 10.07738, 13.1]},
			"faces": {
				"north": {"uv": [5.25, 5.25, 10, 7.25], "texture": "#2"},
				"east": {"uv": [5.25, 5.25, 10, 7.25], "texture": "#2"},
				"south": {"uv": [5.25, 5.25, 10, 7.25], "texture": "#2"},
				"west": {"uv": [5.25, 5.25, 10, 7.25], "texture": "#2"},
				"up": {"uv": [6, 0, 9.5, 4.25], "texture": "#2"},
				"down": {"uv": [6.5, 14.25, 10, 16], "texture": "#2"}
			}
		},
		{
			"from": [8.4, 13.1, 12.7],
			"to": [9.25, 13.45, 13.5],
			"rotation": {"angle": -45, "axis": "y", "origin": [8.82262, 10.07738, 13.1]},
			"faces": {
				"north": {"uv": [5.5, 1, 10.25, 3], "texture": "#2"},
				"east": {"uv": [5.5, 1, 10.25, 3], "texture": "#2"},
				"south": {"uv": [5.5, 1, 10.25, 3], "texture": "#2"},
				"west": {"uv": [5.5, 1, 10.25, 3], "texture": "#2"},
				"up": {"uv": [6, 0, 9.5, 4.25], "texture": "#2"},
				"down": {"uv": [6.5, 14.25, 10, 16], "texture": "#2"}
			}
		},
		{
			"from": [8.4, 13.6, 12.7],
			"to": [9.25, 13.95, 13.5],
			"rotation": {"angle": -45, "axis": "y", "origin": [8.82262, 10.07738, 13.1]},
			"faces": {
				"north": {"uv": [5.5, 9.5, 10.25, 11.5], "texture": "#2"},
				"east": {"uv": [5.5, 9.5, 10.25, 11.5], "texture": "#2"},
				"south": {"uv": [5.5, 9.5, 10.25, 11.5], "texture": "#2"},
				"west": {"uv": [5.5, 9.5, 10.25, 11.5], "texture": "#2"},
				"up": {"uv": [6, 0, 9.5, 4.25], "texture": "#2"},
				"down": {"uv": [6.5, 14.25, 10, 16], "texture": "#2"}
			}
		},
		{
			"from": [8.4, 14.1, 12.7],
			"to": [9.25, 14.45, 13.5],
			"rotation": {"angle": -45, "axis": "y", "origin": [8.82262, 10.07738, 13.1]},
			"faces": {
				"north": {"uv": [5.25, 5.25, 10, 7.25], "texture": "#2"},
				"east": {"uv": [5.25, 5.25, 10, 7.25], "texture": "#2"},
				"south": {"uv": [5.25, 5.25, 10, 7.25], "texture": "#2"},
				"west": {"uv": [5.25, 5.25, 10, 7.25], "texture": "#2"},
				"up": {"uv": [6, 0, 9.5, 4.25], "texture": "#2"},
				"down": {"uv": [6.5, 14.25, 10, 16], "texture": "#2"}
			}
		},
		{
			"from": [8.6, 4.95, 12.95],
			"to": [9, 11.85, 13.25],
			"rotation": {"angle": -45, "axis": "y", "origin": [8.82262, 10.07738, 13.1]},
			"faces": {
				"north": {"uv": [7.75, 1, 8.5, 15], "texture": "#0"},
				"east": {"uv": [7.75, 1, 8.5, 15], "texture": "#0"},
				"south": {"uv": [7.75, 1, 8.5, 15], "texture": "#0"},
				"west": {"uv": [7.75, 1, 8.5, 15], "texture": "#0"},
				"up": {"uv": [7.75, 1, 8.5, 2.5], "texture": "#0"},
				"down": {"uv": [13, 0, 16, 3.25], "texture": "#0"}
			}
		},
		{
			"from": [8.6, -0.1, 12.95],
			"to": [9, 5.1, 13.25],
			"rotation": {"angle": -45, "axis": "y", "origin": [8.82262, 10.07738, 13.1]},
			"faces": {
				"north": {"uv": [7.75, 1, 8.5, 15], "texture": "#0"},
				"east": {"uv": [7.75, 1, 8.5, 15], "texture": "#0"},
				"south": {"uv": [7.75, 1, 8.5, 15], "texture": "#0"},
				"west": {"uv": [7.75, 1, 8.5, 15], "texture": "#0"},
				"up": {"uv": [7.75, 1, 8.5, 2.5], "texture": "#0"},
				"down": {"uv": [13, 0, 16, 3.25], "texture": "#0"}
			}
		},
		{
			"from": [8.725, -0.4, 10.275],
			"to": [8.725, 7.4, 15.625],
			"rotation": {"angle": -45, "axis": "y", "origin": [8.82262, 10.07738, 13.1]},
			"faces": {
				"north": {"uv": [6, 4, 10.5, 12.75], "texture": "#2"},
				"east": {"uv": [0, 0, 16, 16], "texture": "#4"},
				"south": {"uv": [6, 4, 10.5, 12.75], "texture": "#2"},
				"west": {"uv": [0, 0, 16, 16], "texture": "#3"},
				"up": {"uv": [6, 4, 10.5, 6.75], "rotation": 270, "texture": "#2"},
				"down": {"uv": [13, 0, 16, 3.25], "rotation": 90, "texture": "#0"}
			}
		},
		{
			"from": [8.725, 7.2, 10.775],
			"to": [8.725, 13, 15.125],
			"rotation": {"angle": -45, "axis": "y", "origin": [8.82262, 10.07738, 13.1]},
			"faces": {
				"north": {"uv": [6, 4, 10.5, 12.75], "texture": "#2"},
				"east": {"uv": [0, 0, 16, 16], "texture": "#4"},
				"south": {"uv": [6, 4, 10.5, 12.75], "texture": "#2"},
				"west": {"uv": [0, 0, 16, 16], "texture": "#3"},
				"up": {"uv": [6, 4, 10.5, 6.75], "rotation": 270, "texture": "#2"},
				"down": {"uv": [13, 0, 16, 3.25], "rotation": 90, "texture": "#0"}
			}
		},
		{
			"from": [6, -0.4, 13.2],
			"to": [11.35, 7.4, 13.2],
			"rotation": {"angle": -45, "axis": "y", "origin": [8.82262, 10.07738, 13.1]},
			"faces": {
				"north": {"uv": [0, 0, 16, 16], "texture": "#4"},
				"east": {"uv": [6, 4, 10.5, 12.75], "texture": "#2"},
				"south": {"uv": [0, 0, 16, 16], "texture": "#3"},
				"west": {"uv": [6, 4, 10.5, 12.75], "texture": "#2"},
				"up": {"uv": [6, 4, 10.5, 6.75], "rotation": 180, "texture": "#2"},
				"down": {"uv": [13, 0, 16, 3.25], "rotation": 180, "texture": "#0"}
			}
		},
		{
			"from": [6.5, 7.1, 13.2],
			"to": [10.85, 13.6, 13.2],
			"rotation": {"angle": -45, "axis": "y", "origin": [8.82262, 10.07738, 13.1]},
			"faces": {
				"north": {"uv": [0, 0, 16, 16], "texture": "#4"},
				"east": {"uv": [6, 4, 10.5, 12.75], "texture": "#2"},
				"south": {"uv": [0, 0, 16, 16], "texture": "#3"},
				"west": {"uv": [6, 4, 10.5, 12.75], "texture": "#2"},
				"up": {"uv": [6, 4, 10.5, 6.75], "rotation": 180, "texture": "#2"},
				"down": {"uv": [13, 0, 16, 3.25], "rotation": 180, "texture": "#0"}
			}
		},
		{
			"from": [8.925, -0.4, 10.575],
			"to": [8.925, 7.4, 15.925],
			"rotation": {"angle": -45, "axis": "y", "origin": [8.82262, 10.07738, 13.1]},
			"faces": {
				"north": {"uv": [6, 4, 10.5, 12.75], "texture": "#2"},
				"east": {"uv": [0, 0, 16, 16], "texture": "#3"},
				"south": {"uv": [6, 4, 10.5, 12.75], "texture": "#2"},
				"west": {"uv": [0, 0, 16, 16], "texture": "#4"},
				"up": {"uv": [10.5, 6.75, 6, 4], "rotation": 270, "texture": "#2"},
				"down": {"uv": [16, 3.25, 13, 0], "rotation": 90, "texture": "#0"}
			}
		},
		{
			"from": [8.925, 7.2, 11.075],
			"to": [8.925, 13, 15.425],
			"rotation": {"angle": -45, "axis": "y", "origin": [8.82262, 10.07738, 13.1]},
			"faces": {
				"north": {"uv": [6, 4, 10.5, 12.75], "texture": "#2"},
				"east": {"uv": [0, 0, 16, 16], "texture": "#3"},
				"south": {"uv": [6, 4, 10.5, 12.75], "texture": "#2"},
				"west": {"uv": [0, 0, 16, 16], "texture": "#4"},
				"up": {"uv": [10.5, 6.75, 6, 4], "rotation": 270, "texture": "#2"},
				"down": {"uv": [16, 3.25, 13, 0], "rotation": 90, "texture": "#0"}
			}
		},
		{
			"from": [6.3, -0.4, 13],
			"to": [11.65, 7.4, 13],
			"rotation": {"angle": -45, "axis": "y", "origin": [8.82262, 10.07738, 13.1]},
			"faces": {
				"north": {"uv": [0, 0, 16, 16], "texture": "#3"},
				"east": {"uv": [6, 4, 10.5, 12.75], "texture": "#2"},
				"south": {"uv": [0, 0, 16, 16], "texture": "#4"},
				"west": {"uv": [6, 4, 10.5, 12.75], "texture": "#2"},
				"up": {"uv": [10.5, 6.75, 6, 4], "rotation": 180, "texture": "#2"},
				"down": {"uv": [16, 3.25, 13, 0], "rotation": 180, "texture": "#0"}
			}
		},
		{
			"from": [6.8, 7.1, 13],
			"to": [11.15, 13.6, 13],
			"rotation": {"angle": -45, "axis": "y", "origin": [8.82262, 10.07738, 13.1]},
			"faces": {
				"north": {"uv": [0, 0, 16, 16], "texture": "#3"},
				"east": {"uv": [6, 4, 10.5, 12.75], "texture": "#2"},
				"south": {"uv": [0, 0, 16, 16], "texture": "#4"},
				"west": {"uv": [6, 4, 10.5, 12.75], "texture": "#2"},
				"up": {"uv": [10.5, 6.75, 6, 4], "rotation": 180, "texture": "#2"},
				"down": {"uv": [16, 3.25, 13, 0], "rotation": 180, "texture": "#0"}
			}
		},
		{
			"from": [1.95, 11.8, 12.6],
			"to": [2.6, 12.15, 13.2],
			"rotation": {"angle": 22.5, "axis": "y", "origin": [2.27262, 10.07738, 12.9]},
			"faces": {
				"north": {"uv": [6.5, 14.25, 10, 16], "texture": "#2"},
				"east": {"uv": [6.5, 14.25, 10, 16], "texture": "#2"},
				"south": {"uv": [6.5, 14.25, 10, 16], "texture": "#2"},
				"west": {"uv": [6.5, 14.25, 10, 16], "texture": "#2"},
				"down": {"uv": [6.5, 14.25, 10, 16], "texture": "#2"}
			}
		},
		{
			"from": [1.95, 12.3, 12.6],
			"to": [2.6, 12.65, 13.2],
			"rotation": {"angle": 22.5, "axis": "y", "origin": [2.27262, 10.07738, 12.9]},
			"faces": {
				"north": {"uv": [6, 8, 9.5, 9.75], "texture": "#2"},
				"east": {"uv": [6, 8, 9.5, 9.75], "texture": "#2"},
				"south": {"uv": [6, 8, 9.5, 9.75], "texture": "#2"},
				"west": {"uv": [6, 8, 9.5, 9.75], "texture": "#2"}
			}
		},
		{
			"from": [1.95, 12.8, 12.6],
			"to": [2.6, 13.15, 13.2],
			"rotation": {"angle": 22.5, "axis": "y", "origin": [2.27262, 10.07738, 12.9]},
			"faces": {
				"north": {"uv": [5.5, 3.5, 9, 5.25], "texture": "#2"},
				"east": {"uv": [5.5, 3.5, 9, 5.25], "texture": "#2"},
				"south": {"uv": [5.5, 3.5, 9, 5.25], "texture": "#2"},
				"west": {"uv": [5.5, 3.5, 9, 5.25], "texture": "#2"}
			}
		},
		{
			"from": [1.95, 13.3, 12.6],
			"to": [2.6, 13.65, 13.2],
			"rotation": {"angle": 22.5, "axis": "y", "origin": [2.27262, 10.07738, 12.9]},
			"faces": {
				"north": {"uv": [5.75, 12.5, 9.25, 14.25], "texture": "#2"},
				"east": {"uv": [5.75, 12.5, 9.25, 14.25], "texture": "#2"},
				"south": {"uv": [5.75, 12.5, 9.25, 14.25], "texture": "#2"},
				"west": {"uv": [5.75, 12.5, 9.25, 14.25], "texture": "#2"}
			}
		},
		{
			"from": [1.95, 13.8, 12.6],
			"to": [2.6, 14.15, 13.2],
			"rotation": {"angle": 22.5, "axis": "y", "origin": [2.27262, 10.07738, 12.9]},
			"faces": {
				"north": {"uv": [5.75, 4, 9.25, 5.75], "texture": "#2"},
				"east": {"uv": [5.75, 4, 9.25, 5.75], "texture": "#2"},
				"south": {"uv": [5.75, 4, 9.25, 5.75], "texture": "#2"},
				"west": {"uv": [5.75, 4, 9.25, 5.75], "texture": "#2"}
			}
		},
		{
			"from": [1.95, 14.4, 12.6],
			"to": [2.6, 14.75, 13.2],
			"rotation": {"angle": 22.5, "axis": "y", "origin": [2.27262, 10.07738, 12.9]},
			"faces": {
				"north": {"uv": [5.75, 0, 9.25, 1.75], "texture": "#2"},
				"east": {"uv": [5.75, 0, 9.25, 1.75], "texture": "#2"},
				"south": {"uv": [5.75, 0, 9.25, 1.75], "texture": "#2"},
				"west": {"uv": [5.75, 0, 9.25, 1.75], "texture": "#2"},
				"up": {"uv": [5.75, 0, 9.25, 3], "texture": "#2"}
			}
		},
		{
			"from": [1.85, 12.1, 12.5],
			"to": [2.7, 12.45, 13.3],
			"rotation": {"angle": 22.5, "axis": "y", "origin": [2.27262, 10.07738, 12.9]},
			"faces": {
				"north": {"uv": [5.5, 11.75, 10.25, 13.75], "texture": "#2"},
				"east": {"uv": [5.5, 11.75, 10.25, 13.75], "texture": "#2"},
				"south": {"uv": [5.5, 11.75, 10.25, 13.75], "texture": "#2"},
				"west": {"uv": [5.5, 11.75, 10.25, 13.75], "texture": "#2"},
				"up": {"uv": [6, 0, 9.5, 4.25], "texture": "#2"},
				"down": {"uv": [6.5, 14.25, 10, 16], "texture": "#2"}
			}
		},
		{
			"from": [1.85, 12.6, 12.5],
			"to": [2.7, 12.95, 13.3],
			"rotation": {"angle": 22.5, "axis": "y", "origin": [2.27262, 10.07738, 12.9]},
			"faces": {
				"north": {"uv": [5.25, 5.25, 10, 7.25], "texture": "#2"},
				"east": {"uv": [5.25, 5.25, 10, 7.25], "texture": "#2"},
				"south": {"uv": [5.25, 5.25, 10, 7.25], "texture": "#2"},
				"west": {"uv": [5.25, 5.25, 10, 7.25], "texture": "#2"},
				"up": {"uv": [6, 0, 9.5, 4.25], "texture": "#2"},
				"down": {"uv": [6.5, 14.25, 10, 16], "texture": "#2"}
			}
		},
		{
			"from": [1.85, 13.1, 12.5],
			"to": [2.7, 13.45, 13.3],
			"rotation": {"angle": 22.5, "axis": "y", "origin": [2.27262, 10.07738, 12.9]},
			"faces": {
				"north": {"uv": [5.5, 1, 10.25, 3], "texture": "#2"},
				"east": {"uv": [5.5, 1, 10.25, 3], "texture": "#2"},
				"south": {"uv": [5.5, 1, 10.25, 3], "texture": "#2"},
				"west": {"uv": [5.5, 1, 10.25, 3], "texture": "#2"},
				"up": {"uv": [6, 0, 9.5, 4.25], "texture": "#2"},
				"down": {"uv": [6.5, 14.25, 10, 16], "texture": "#2"}
			}
		},
		{
			"from": [1.85, 13.6, 12.5],
			"to": [2.7, 13.95, 13.3],
			"rotation": {"angle": 22.5, "axis": "y", "origin": [2.27262, 10.07738, 12.9]},
			"faces": {
				"north": {"uv": [5.5, 9.5, 10.25, 11.5], "texture": "#2"},
				"east": {"uv": [5.5, 9.5, 10.25, 11.5], "texture": "#2"},
				"south": {"uv": [5.5, 9.5, 10.25, 11.5], "texture": "#2"},
				"west": {"uv": [5.5, 9.5, 10.25, 11.5], "texture": "#2"},
				"up": {"uv": [6, 0, 9.5, 4.25], "texture": "#2"},
				"down": {"uv": [6.5, 14.25, 10, 16], "texture": "#2"}
			}
		},
		{
			"from": [1.85, 14.1, 12.5],
			"to": [2.7, 14.45, 13.3],
			"rotation": {"angle": 22.5, "axis": "y", "origin": [2.27262, 10.07738, 12.9]},
			"faces": {
				"north": {"uv": [5.25, 5.25, 10, 7.25], "texture": "#2"},
				"east": {"uv": [5.25, 5.25, 10, 7.25], "texture": "#2"},
				"south": {"uv": [5.25, 5.25, 10, 7.25], "texture": "#2"},
				"west": {"uv": [5.25, 5.25, 10, 7.25], "texture": "#2"},
				"up": {"uv": [6, 0, 9.5, 4.25], "texture": "#2"},
				"down": {"uv": [6.5, 14.25, 10, 16], "texture": "#2"}
			}
		},
		{
			"from": [2.05, 4.95, 12.75],
			"to": [2.45, 11.85, 13.05],
			"rotation": {"angle": 22.5, "axis": "y", "origin": [2.27262, 10.07738, 12.9]},
			"faces": {
				"north": {"uv": [7.75, 1, 8.5, 15], "texture": "#0"},
				"east": {"uv": [7.75, 1, 8.5, 15], "texture": "#0"},
				"south": {"uv": [7.75, 1, 8.5, 15], "texture": "#0"},
				"west": {"uv": [7.75, 1, 8.5, 15], "texture": "#0"},
				"up": {"uv": [7.75, 1, 8.5, 2.5], "texture": "#0"},
				"down": {"uv": [13, 0, 16, 3.25], "texture": "#0"}
			}
		},
		{
			"from": [2.05, -0.1, 12.75],
			"to": [2.45, 5.1, 13.05],
			"rotation": {"angle": 22.5, "axis": "y", "origin": [2.27262, 10.07738, 12.9]},
			"faces": {
				"north": {"uv": [7.75, 1, 8.5, 15], "texture": "#0"},
				"east": {"uv": [7.75, 1, 8.5, 15], "texture": "#0"},
				"south": {"uv": [7.75, 1, 8.5, 15], "texture": "#0"},
				"west": {"uv": [7.75, 1, 8.5, 15], "texture": "#0"},
				"up": {"uv": [7.75, 1, 8.5, 2.5], "texture": "#0"},
				"down": {"uv": [13, 0, 16, 3.25], "texture": "#0"}
			}
		},
		{
			"from": [2.175, -0.4, 10.075],
			"to": [2.175, 7.4, 15.425],
			"rotation": {"angle": 22.5, "axis": "y", "origin": [2.27262, 10.07738, 12.9]},
			"faces": {
				"north": {"uv": [6, 4, 10.5, 12.75], "texture": "#2"},
				"east": {"uv": [0, 0, 16, 16], "texture": "#4"},
				"south": {"uv": [6, 4, 10.5, 12.75], "texture": "#2"},
				"west": {"uv": [0, 0, 16, 16], "texture": "#3"},
				"up": {"uv": [6, 4, 10.5, 6.75], "rotation": 270, "texture": "#2"},
				"down": {"uv": [13, 0, 16, 3.25], "rotation": 90, "texture": "#0"}
			}
		},
		{
			"from": [2.175, 7.2, 10.575],
			"to": [2.175, 13, 14.925],
			"rotation": {"angle": 22.5, "axis": "y", "origin": [2.27262, 10.07738, 12.9]},
			"faces": {
				"north": {"uv": [6, 4, 10.5, 12.75], "texture": "#2"},
				"east": {"uv": [0, 0, 16, 16], "texture": "#4"},
				"south": {"uv": [6, 4, 10.5, 12.75], "texture": "#2"},
				"west": {"uv": [0, 0, 16, 16], "texture": "#3"},
				"up": {"uv": [6, 4, 10.5, 6.75], "rotation": 270, "texture": "#2"},
				"down": {"uv": [13, 0, 16, 3.25], "rotation": 90, "texture": "#0"}
			}
		},
		{
			"from": [-0.55, -0.4, 13],
			"to": [4.8, 7.4, 13],
			"rotation": {"angle": 22.5, "axis": "y", "origin": [2.27262, 10.07738, 12.9]},
			"faces": {
				"north": {"uv": [0, 0, 16, 16], "texture": "#4"},
				"east": {"uv": [6, 4, 10.5, 12.75], "texture": "#2"},
				"south": {"uv": [0, 0, 16, 16], "texture": "#3"},
				"west": {"uv": [6, 4, 10.5, 12.75], "texture": "#2"},
				"up": {"uv": [6, 4, 10.5, 6.75], "rotation": 180, "texture": "#2"},
				"down": {"uv": [13, 0, 16, 3.25], "rotation": 180, "texture": "#0"}
			}
		},
		{
			"from": [-0.05, 7.1, 13],
			"to": [4.3, 13.6, 13],
			"rotation": {"angle": 22.5, "axis": "y", "origin": [2.27262, 10.07738, 12.9]},
			"faces": {
				"north": {"uv": [0, 0, 16, 16], "texture": "#4"},
				"east": {"uv": [6, 4, 10.5, 12.75], "texture": "#2"},
				"south": {"uv": [0, 0, 16, 16], "texture": "#3"},
				"west": {"uv": [6, 4, 10.5, 12.75], "texture": "#2"},
				"up": {"uv": [6, 4, 10.5, 6.75], "rotation": 180, "texture": "#2"},
				"down": {"uv": [13, 0, 16, 3.25], "rotation": 180, "texture": "#0"}
			}
		},
		{
			"from": [2.375, -0.4, 10.375],
			"to": [2.375, 7.4, 15.725],
			"rotation": {"angle": 22.5, "axis": "y", "origin": [2.27262, 10.07738, 12.9]},
			"faces": {
				"north": {"uv": [6, 4, 10.5, 12.75], "texture": "#2"},
				"east": {"uv": [0, 0, 16, 16], "texture": "#3"},
				"south": {"uv": [6, 4, 10.5, 12.75], "texture": "#2"},
				"west": {"uv": [0, 0, 16, 16], "texture": "#4"},
				"up": {"uv": [10.5, 6.75, 6, 4], "rotation": 270, "texture": "#2"},
				"down": {"uv": [16, 3.25, 13, 0], "rotation": 90, "texture": "#0"}
			}
		},
		{
			"from": [2.375, 7.2, 10.875],
			"to": [2.375, 13, 15.225],
			"rotation": {"angle": 22.5, "axis": "y", "origin": [2.27262, 10.07738, 12.9]},
			"faces": {
				"north": {"uv": [6, 4, 10.5, 12.75], "texture": "#2"},
				"east": {"uv": [0, 0, 16, 16], "texture": "#3"},
				"south": {"uv": [6, 4, 10.5, 12.75], "texture": "#2"},
				"west": {"uv": [0, 0, 16, 16], "texture": "#4"},
				"up": {"uv": [10.5, 6.75, 6, 4], "rotation": 270, "texture": "#2"},
				"down": {"uv": [16, 3.25, 13, 0], "rotation": 90, "texture": "#0"}
			}
		},
		{
			"from": [-0.25, -0.4, 12.8],
			"to": [5.1, 7.4, 12.8],
			"rotation": {"angle": 22.5, "axis": "y", "origin": [2.27262, 10.07738, 12.9]},
			"faces": {
				"north": {"uv": [0, 0, 16, 16], "texture": "#3"},
				"east": {"uv": [6, 4, 10.5, 12.75], "texture": "#2"},
				"south": {"uv": [0, 0, 16, 16], "texture": "#4"},
				"west": {"uv": [6, 4, 10.5, 12.75], "texture": "#2"},
				"up": {"uv": [10.5, 6.75, 6, 4], "rotation": 180, "texture": "#2"},
				"down": {"uv": [16, 3.25, 13, 0], "rotation": 180, "texture": "#0"}
			}
		},
		{
			"from": [0.25, 7.1, 12.8],
			"to": [4.6, 13.6, 12.8],
			"rotation": {"angle": 22.5, "axis": "y", "origin": [2.27262, 10.07738, 12.9]},
			"faces": {
				"north": {"uv": [0, 0, 16, 16], "texture": "#3"},
				"east": {"uv": [6, 4, 10.5, 12.75], "texture": "#2"},
				"south": {"uv": [0, 0, 16, 16], "texture": "#4"},
				"west": {"uv": [6, 4, 10.5, 12.75], "texture": "#2"},
				"up": {"uv": [10.5, 6.75, 6, 4], "rotation": 180, "texture": "#2"},
				"down": {"uv": [16, 3.25, 13, 0], "rotation": 180, "texture": "#0"}
			}
		},
		{
			"from": [2.55, 11.8, 7],
			"to": [3.2, 12.15, 7.6],
			"rotation": {"angle": -22.5, "axis": "y", "origin": [2.87262, 10.07738, 7.3]},
			"faces": {
				"north": {"uv": [6.5, 14.25, 10, 16], "texture": "#2"},
				"east": {"uv": [6.5, 14.25, 10, 16], "texture": "#2"},
				"south": {"uv": [6.5, 14.25, 10, 16], "texture": "#2"},
				"west": {"uv": [6.5, 14.25, 10, 16], "texture": "#2"},
				"down": {"uv": [6.5, 14.25, 10, 16], "texture": "#2"}
			}
		},
		{
			"from": [2.55, 12.3, 7],
			"to": [3.2, 12.65, 7.6],
			"rotation": {"angle": -22.5, "axis": "y", "origin": [2.87262, 10.07738, 7.3]},
			"faces": {
				"north": {"uv": [6, 8, 9.5, 9.75], "texture": "#2"},
				"east": {"uv": [6, 8, 9.5, 9.75], "texture": "#2"},
				"south": {"uv": [6, 8, 9.5, 9.75], "texture": "#2"},
				"west": {"uv": [6, 8, 9.5, 9.75], "texture": "#2"}
			}
		},
		{
			"from": [2.55, 12.8, 7],
			"to": [3.2, 13.15, 7.6],
			"rotation": {"angle": -22.5, "axis": "y", "origin": [2.87262, 10.07738, 7.3]},
			"faces": {
				"north": {"uv": [5.5, 3.5, 9, 5.25], "texture": "#2"},
				"east": {"uv": [5.5, 3.5, 9, 5.25], "texture": "#2"},
				"south": {"uv": [5.5, 3.5, 9, 5.25], "texture": "#2"},
				"west": {"uv": [5.5, 3.5, 9, 5.25], "texture": "#2"}
			}
		},
		{
			"from": [2.55, 13.3, 7],
			"to": [3.2, 13.65, 7.6],
			"rotation": {"angle": -22.5, "axis": "y", "origin": [2.87262, 10.07738, 7.3]},
			"faces": {
				"north": {"uv": [5.75, 12.5, 9.25, 14.25], "texture": "#2"},
				"east": {"uv": [5.75, 12.5, 9.25, 14.25], "texture": "#2"},
				"south": {"uv": [5.75, 12.5, 9.25, 14.25], "texture": "#2"},
				"west": {"uv": [5.75, 12.5, 9.25, 14.25], "texture": "#2"}
			}
		},
		{
			"from": [2.55, 13.8, 7],
			"to": [3.2, 14.15, 7.6],
			"rotation": {"angle": -22.5, "axis": "y", "origin": [2.87262, 10.07738, 7.3]},
			"faces": {
				"north": {"uv": [5.75, 4, 9.25, 5.75], "texture": "#2"},
				"east": {"uv": [5.75, 4, 9.25, 5.75], "texture": "#2"},
				"south": {"uv": [5.75, 4, 9.25, 5.75], "texture": "#2"},
				"west": {"uv": [5.75, 4, 9.25, 5.75], "texture": "#2"}
			}
		},
		{
			"from": [2.55, 14.4, 7],
			"to": [3.2, 14.75, 7.6],
			"rotation": {"angle": -22.5, "axis": "y", "origin": [2.87262, 10.07738, 7.3]},
			"faces": {
				"north": {"uv": [5.75, 0, 9.25, 1.75], "texture": "#2"},
				"east": {"uv": [5.75, 0, 9.25, 1.75], "texture": "#2"},
				"south": {"uv": [5.75, 0, 9.25, 1.75], "texture": "#2"},
				"west": {"uv": [5.75, 0, 9.25, 1.75], "texture": "#2"},
				"up": {"uv": [5.75, 0, 9.25, 3], "texture": "#2"}
			}
		},
		{
			"from": [2.45, 12.1, 6.9],
			"to": [3.3, 12.45, 7.7],
			"rotation": {"angle": -22.5, "axis": "y", "origin": [2.87262, 10.07738, 7.3]},
			"faces": {
				"north": {"uv": [5.5, 11.75, 10.25, 13.75], "texture": "#2"},
				"east": {"uv": [5.5, 11.75, 10.25, 13.75], "texture": "#2"},
				"south": {"uv": [5.5, 11.75, 10.25, 13.75], "texture": "#2"},
				"west": {"uv": [5.5, 11.75, 10.25, 13.75], "texture": "#2"},
				"up": {"uv": [6, 0, 9.5, 4.25], "texture": "#2"},
				"down": {"uv": [6.5, 14.25, 10, 16], "texture": "#2"}
			}
		},
		{
			"from": [2.45, 12.6, 6.9],
			"to": [3.3, 12.95, 7.7],
			"rotation": {"angle": -22.5, "axis": "y", "origin": [2.87262, 10.07738, 7.3]},
			"faces": {
				"north": {"uv": [5.25, 5.25, 10, 7.25], "texture": "#2"},
				"east": {"uv": [5.25, 5.25, 10, 7.25], "texture": "#2"},
				"south": {"uv": [5.25, 5.25, 10, 7.25], "texture": "#2"},
				"west": {"uv": [5.25, 5.25, 10, 7.25], "texture": "#2"},
				"up": {"uv": [6, 0, 9.5, 4.25], "texture": "#2"},
				"down": {"uv": [6.5, 14.25, 10, 16], "texture": "#2"}
			}
		},
		{
			"from": [2.45, 13.1, 6.9],
			"to": [3.3, 13.45, 7.7],
			"rotation": {"angle": -22.5, "axis": "y", "origin": [2.87262, 10.07738, 7.3]},
			"faces": {
				"north": {"uv": [5.5, 1, 10.25, 3], "texture": "#2"},
				"east": {"uv": [5.5, 1, 10.25, 3], "texture": "#2"},
				"south": {"uv": [5.5, 1, 10.25, 3], "texture": "#2"},
				"west": {"uv": [5.5, 1, 10.25, 3], "texture": "#2"},
				"up": {"uv": [6, 0, 9.5, 4.25], "texture": "#2"},
				"down": {"uv": [6.5, 14.25, 10, 16], "texture": "#2"}
			}
		},
		{
			"from": [2.45, 13.6, 6.9],
			"to": [3.3, 13.95, 7.7],
			"rotation": {"angle": -22.5, "axis": "y", "origin": [2.87262, 10.07738, 7.3]},
			"faces": {
				"north": {"uv": [5.5, 9.5, 10.25, 11.5], "texture": "#2"},
				"east": {"uv": [5.5, 9.5, 10.25, 11.5], "texture": "#2"},
				"south": {"uv": [5.5, 9.5, 10.25, 11.5], "texture": "#2"},
				"west": {"uv": [5.5, 9.5, 10.25, 11.5], "texture": "#2"},
				"up": {"uv": [6, 0, 9.5, 4.25], "texture": "#2"},
				"down": {"uv": [6.5, 14.25, 10, 16], "texture": "#2"}
			}
		},
		{
			"from": [2.45, 14.1, 6.9],
			"to": [3.3, 14.45, 7.7],
			"rotation": {"angle": -22.5, "axis": "y", "origin": [2.87262, 10.07738, 7.3]},
			"faces": {
				"north": {"uv": [5.25, 5.25, 10, 7.25], "texture": "#2"},
				"east": {"uv": [5.25, 5.25, 10, 7.25], "texture": "#2"},
				"south": {"uv": [5.25, 5.25, 10, 7.25], "texture": "#2"},
				"west": {"uv": [5.25, 5.25, 10, 7.25], "texture": "#2"},
				"up": {"uv": [6, 0, 9.5, 4.25], "texture": "#2"},
				"down": {"uv": [6.5, 14.25, 10, 16], "texture": "#2"}
			}
		},
		{
			"from": [2.65, 4.95, 7.15],
			"to": [3.05, 11.85, 7.45],
			"rotation": {"angle": -22.5, "axis": "y", "origin": [2.87262, 10.07738, 7.3]},
			"faces": {
				"north": {"uv": [7.75, 1, 8.5, 15], "texture": "#0"},
				"east": {"uv": [7.75, 1, 8.5, 15], "texture": "#0"},
				"south": {"uv": [7.75, 1, 8.5, 15], "texture": "#0"},
				"west": {"uv": [7.75, 1, 8.5, 15], "texture": "#0"},
				"up": {"uv": [7.75, 1, 8.5, 2.5], "texture": "#0"},
				"down": {"uv": [13, 0, 16, 3.25], "texture": "#0"}
			}
		},
		{
			"from": [2.65, -0.1, 7.15],
			"to": [3.05, 5.1, 7.45],
			"rotation": {"angle": -22.5, "axis": "y", "origin": [2.87262, 10.07738, 7.3]},
			"faces": {
				"north": {"uv": [7.75, 1, 8.5, 15], "texture": "#0"},
				"east": {"uv": [7.75, 1, 8.5, 15], "texture": "#0"},
				"south": {"uv": [7.75, 1, 8.5, 15], "texture": "#0"},
				"west": {"uv": [7.75, 1, 8.5, 15], "texture": "#0"},
				"up": {"uv": [7.75, 1, 8.5, 2.5], "texture": "#0"},
				"down": {"uv": [13, 0, 16, 3.25], "texture": "#0"}
			}
		},
		{
			"from": [2.775, -0.4, 4.475],
			"to": [2.775, 7.4, 9.825],
			"rotation": {"angle": -22.5, "axis": "y", "origin": [2.87262, 10.07738, 7.3]},
			"faces": {
				"north": {"uv": [6, 4, 10.5, 12.75], "texture": "#2"},
				"east": {"uv": [0, 0, 16, 16], "texture": "#4"},
				"south": {"uv": [6, 4, 10.5, 12.75], "texture": "#2"},
				"west": {"uv": [0, 0, 16, 16], "texture": "#3"},
				"up": {"uv": [6, 4, 10.5, 6.75], "rotation": 270, "texture": "#2"},
				"down": {"uv": [13, 0, 16, 3.25], "rotation": 90, "texture": "#0"}
			}
		},
		{
			"from": [2.775, 7.2, 4.975],
			"to": [2.775, 13, 9.325],
			"rotation": {"angle": -22.5, "axis": "y", "origin": [2.87262, 10.07738, 7.3]},
			"faces": {
				"north": {"uv": [6, 4, 10.5, 12.75], "texture": "#2"},
				"east": {"uv": [0, 0, 16, 16], "texture": "#4"},
				"south": {"uv": [6, 4, 10.5, 12.75], "texture": "#2"},
				"west": {"uv": [0, 0, 16, 16], "texture": "#3"},
				"up": {"uv": [6, 4, 10.5, 6.75], "rotation": 270, "texture": "#2"},
				"down": {"uv": [13, 0, 16, 3.25], "rotation": 90, "texture": "#0"}
			}
		},
		{
			"from": [0.05, -0.4, 7.4],
			"to": [5.4, 7.4, 7.4],
			"rotation": {"angle": -22.5, "axis": "y", "origin": [2.87262, 10.07738, 7.3]},
			"faces": {
				"north": {"uv": [0, 0, 16, 16], "texture": "#4"},
				"east": {"uv": [6, 4, 10.5, 12.75], "texture": "#2"},
				"south": {"uv": [0, 0, 16, 16], "texture": "#3"},
				"west": {"uv": [6, 4, 10.5, 12.75], "texture": "#2"},
				"up": {"uv": [6, 4, 10.5, 6.75], "rotation": 180, "texture": "#2"},
				"down": {"uv": [13, 0, 16, 3.25], "rotation": 180, "texture": "#0"}
			}
		},
		{
			"from": [0.55, 7.1, 7.4],
			"to": [4.9, 13.6, 7.4],
			"rotation": {"angle": -22.5, "axis": "y", "origin": [2.87262, 10.07738, 7.3]},
			"faces": {
				"north": {"uv": [0, 0, 16, 16], "texture": "#4"},
				"east": {"uv": [6, 4, 10.5, 12.75], "texture": "#2"},
				"south": {"uv": [0, 0, 16, 16], "texture": "#3"},
				"west": {"uv": [6, 4, 10.5, 12.75], "texture": "#2"},
				"up": {"uv": [6, 4, 10.5, 6.75], "rotation": 180, "texture": "#2"},
				"down": {"uv": [13, 0, 16, 3.25], "rotation": 180, "texture": "#0"}
			}
		},
		{
			"from": [2.975, -0.4, 4.775],
			"to": [2.975, 7.4, 10.125],
			"rotation": {"angle": -22.5, "axis": "y", "origin": [2.87262, 10.07738, 7.3]},
			"faces": {
				"north": {"uv": [6, 4, 10.5, 12.75], "texture": "#2"},
				"east": {"uv": [0, 0, 16, 16], "texture": "#3"},
				"south": {"uv": [6, 4, 10.5, 12.75], "texture": "#2"},
				"west": {"uv": [0, 0, 16, 16], "texture": "#4"},
				"up": {"uv": [10.5, 6.75, 6, 4], "rotation": 270, "texture": "#2"},
				"down": {"uv": [16, 3.25, 13, 0], "rotation": 90, "texture": "#0"}
			}
		},
		{
			"from": [2.975, 7.2, 5.275],
			"to": [2.975, 13, 9.625],
			"rotation": {"angle": -22.5, "axis": "y", "origin": [2.87262, 10.07738, 7.3]},
			"faces": {
				"north": {"uv": [6, 4, 10.5, 12.75], "texture": "#2"},
				"east": {"uv": [0, 0, 16, 16], "texture": "#3"},
				"south": {"uv": [6, 4, 10.5, 12.75], "texture": "#2"},
				"west": {"uv": [0, 0, 16, 16], "texture": "#4"},
				"up": {"uv": [10.5, 6.75, 6, 4], "rotation": 270, "texture": "#2"},
				"down": {"uv": [16, 3.25, 13, 0], "rotation": 90, "texture": "#0"}
			}
		},
		{
			"from": [0.35, -0.4, 7.2],
			"to": [5.7, 7.4, 7.2],
			"rotation": {"angle": -22.5, "axis": "y", "origin": [2.87262, 10.07738, 7.3]},
			"faces": {
				"north": {"uv": [0, 0, 16, 16], "texture": "#3"},
				"east": {"uv": [6, 4, 10.5, 12.75], "texture": "#2"},
				"south": {"uv": [0, 0, 16, 16], "texture": "#4"},
				"west": {"uv": [6, 4, 10.5, 12.75], "texture": "#2"},
				"up": {"uv": [10.5, 6.75, 6, 4], "rotation": 180, "texture": "#2"},
				"down": {"uv": [16, 3.25, 13, 0], "rotation": 180, "texture": "#0"}
			}
		},
		{
			"from": [0.85, 7.1, 7.2],
			"to": [5.2, 13.6, 7.2],
			"rotation": {"angle": -22.5, "axis": "y", "origin": [2.87262, 10.07738, 7.3]},
			"faces": {
				"north": {"uv": [0, 0, 16, 16], "texture": "#3"},
				"east": {"uv": [6, 4, 10.5, 12.75], "texture": "#2"},
				"south": {"uv": [0, 0, 16, 16], "texture": "#4"},
				"west": {"uv": [6, 4, 10.5, 12.75], "texture": "#2"},
				"up": {"uv": [10.5, 6.75, 6, 4], "rotation": 180, "texture": "#2"},
				"down": {"uv": [16, 3.25, 13, 0], "rotation": 180, "texture": "#0"}
			}
		},
		{
			"from": [13.25, 11.8, 13.75],
			"to": [13.9, 12.15, 14.35],
			"rotation": {"angle": -22.5, "axis": "y", "origin": [13.57262, 10.07738, 14.05]},
			"faces": {
				"north": {"uv": [6.5, 14.25, 10, 16], "texture": "#2"},
				"east": {"uv": [6.5, 14.25, 10, 16], "texture": "#2"},
				"south": {"uv": [6.5, 14.25, 10, 16], "texture": "#2"},
				"west": {"uv": [6.5, 14.25, 10, 16], "texture": "#2"},
				"down": {"uv": [6.5, 14.25, 10, 16], "texture": "#2"}
			}
		},
		{
			"from": [13.25, 12.3, 13.75],
			"to": [13.9, 12.65, 14.35],
			"rotation": {"angle": -22.5, "axis": "y", "origin": [13.57262, 10.07738, 14.05]},
			"faces": {
				"north": {"uv": [6, 8, 9.5, 9.75], "texture": "#2"},
				"east": {"uv": [6, 8, 9.5, 9.75], "texture": "#2"},
				"south": {"uv": [6, 8, 9.5, 9.75], "texture": "#2"},
				"west": {"uv": [6, 8, 9.5, 9.75], "texture": "#2"}
			}
		},
		{
			"from": [13.25, 12.8, 13.75],
			"to": [13.9, 13.15, 14.35],
			"rotation": {"angle": -22.5, "axis": "y", "origin": [13.57262, 10.07738, 14.05]},
			"faces": {
				"north": {"uv": [5.5, 3.5, 9, 5.25], "texture": "#2"},
				"east": {"uv": [5.5, 3.5, 9, 5.25], "texture": "#2"},
				"south": {"uv": [5.5, 3.5, 9, 5.25], "texture": "#2"},
				"west": {"uv": [5.5, 3.5, 9, 5.25], "texture": "#2"}
			}
		},
		{
			"from": [13.25, 13.3, 13.75],
			"to": [13.9, 13.65, 14.35],
			"rotation": {"angle": -22.5, "axis": "y", "origin": [13.57262, 10.07738, 14.05]},
			"faces": {
				"north": {"uv": [5.75, 12.5, 9.25, 14.25], "texture": "#2"},
				"east": {"uv": [5.75, 12.5, 9.25, 14.25], "texture": "#2"},
				"south": {"uv": [5.75, 12.5, 9.25, 14.25], "texture": "#2"},
				"west": {"uv": [5.75, 12.5, 9.25, 14.25], "texture": "#2"}
			}
		},
		{
			"from": [13.25, 13.8, 13.75],
			"to": [13.9, 14.15, 14.35],
			"rotation": {"angle": -22.5, "axis": "y", "origin": [13.57262, 10.07738, 14.05]},
			"faces": {
				"north": {"uv": [5.75, 4, 9.25, 5.75], "texture": "#2"},
				"east": {"uv": [5.75, 4, 9.25, 5.75], "texture": "#2"},
				"south": {"uv": [5.75, 4, 9.25, 5.75], "texture": "#2"},
				"west": {"uv": [5.75, 4, 9.25, 5.75], "texture": "#2"}
			}
		},
		{
			"from": [13.25, 14.4, 13.75],
			"to": [13.9, 14.75, 14.35],
			"rotation": {"angle": -22.5, "axis": "y", "origin": [13.57262, 10.07738, 14.05]},
			"faces": {
				"north": {"uv": [5.75, 0, 9.25, 1.75], "texture": "#2"},
				"east": {"uv": [5.75, 0, 9.25, 1.75], "texture": "#2"},
				"south": {"uv": [5.75, 0, 9.25, 1.75], "texture": "#2"},
				"west": {"uv": [5.75, 0, 9.25, 1.75], "texture": "#2"},
				"up": {"uv": [5.75, 0, 9.25, 3], "texture": "#2"}
			}
		},
		{
			"from": [13.15, 12.1, 13.65],
			"to": [14, 12.45, 14.45],
			"rotation": {"angle": -22.5, "axis": "y", "origin": [13.57262, 10.07738, 14.05]},
			"faces": {
				"north": {"uv": [5.5, 11.75, 10.25, 13.75], "texture": "#2"},
				"east": {"uv": [5.5, 11.75, 10.25, 13.75], "texture": "#2"},
				"south": {"uv": [5.5, 11.75, 10.25, 13.75], "texture": "#2"},
				"west": {"uv": [5.5, 11.75, 10.25, 13.75], "texture": "#2"},
				"up": {"uv": [6, 0, 9.5, 4.25], "texture": "#2"},
				"down": {"uv": [6.5, 14.25, 10, 16], "texture": "#2"}
			}
		},
		{
			"from": [13.15, 12.6, 13.65],
			"to": [14, 12.95, 14.45],
			"rotation": {"angle": -22.5, "axis": "y", "origin": [13.57262, 10.07738, 14.05]},
			"faces": {
				"north": {"uv": [5.25, 5.25, 10, 7.25], "texture": "#2"},
				"east": {"uv": [5.25, 5.25, 10, 7.25], "texture": "#2"},
				"south": {"uv": [5.25, 5.25, 10, 7.25], "texture": "#2"},
				"west": {"uv": [5.25, 5.25, 10, 7.25], "texture": "#2"},
				"up": {"uv": [6, 0, 9.5, 4.25], "texture": "#2"},
				"down": {"uv": [6.5, 14.25, 10, 16], "texture": "#2"}
			}
		},
		{
			"from": [13.15, 13.1, 13.65],
			"to": [14, 13.45, 14.45],
			"rotation": {"angle": -22.5, "axis": "y", "origin": [13.57262, 10.07738, 14.05]},
			"faces": {
				"north": {"uv": [5.5, 1, 10.25, 3], "texture": "#2"},
				"east": {"uv": [5.5, 1, 10.25, 3], "texture": "#2"},
				"south": {"uv": [5.5, 1, 10.25, 3], "texture": "#2"},
				"west": {"uv": [5.5, 1, 10.25, 3], "texture": "#2"},
				"up": {"uv": [6, 0, 9.5, 4.25], "texture": "#2"},
				"down": {"uv": [6.5, 14.25, 10, 16], "texture": "#2"}
			}
		},
		{
			"from": [13.15, 13.6, 13.65],
			"to": [14, 13.95, 14.45],
			"rotation": {"angle": -22.5, "axis": "y", "origin": [13.57262, 10.07738, 14.05]},
			"faces": {
				"north": {"uv": [5.5, 9.5, 10.25, 11.5], "texture": "#2"},
				"east": {"uv": [5.5, 9.5, 10.25, 11.5], "texture": "#2"},
				"south": {"uv": [5.5, 9.5, 10.25, 11.5], "texture": "#2"},
				"west": {"uv": [5.5, 9.5, 10.25, 11.5], "texture": "#2"},
				"up": {"uv": [6, 0, 9.5, 4.25], "texture": "#2"},
				"down": {"uv": [6.5, 14.25, 10, 16], "texture": "#2"}
			}
		},
		{
			"from": [13.15, 14.1, 13.65],
			"to": [14, 14.45, 14.45],
			"rotation": {"angle": -22.5, "axis": "y", "origin": [13.57262, 10.07738, 14.05]},
			"faces": {
				"north": {"uv": [5.25, 5.25, 10, 7.25], "texture": "#2"},
				"east": {"uv": [5.25, 5.25, 10, 7.25], "texture": "#2"},
				"south": {"uv": [5.25, 5.25, 10, 7.25], "texture": "#2"},
				"west": {"uv": [5.25, 5.25, 10, 7.25], "texture": "#2"},
				"up": {"uv": [6, 0, 9.5, 4.25], "texture": "#2"},
				"down": {"uv": [6.5, 14.25, 10, 16], "texture": "#2"}
			}
		},
		{
			"from": [13.35, 4.95, 13.9],
			"to": [13.75, 11.85, 14.2],
			"rotation": {"angle": -22.5, "axis": "y", "origin": [13.57262, 10.07738, 14.05]},
			"faces": {
				"north": {"uv": [7.75, 1, 8.5, 15], "texture": "#0"},
				"east": {"uv": [7.75, 1, 8.5, 15], "texture": "#0"},
				"south": {"uv": [7.75, 1, 8.5, 15], "texture": "#0"},
				"west": {"uv": [7.75, 1, 8.5, 15], "texture": "#0"},
				"up": {"uv": [7.75, 1, 8.5, 2.5], "texture": "#0"},
				"down": {"uv": [13, 0, 16, 3.25], "texture": "#0"}
			}
		},
		{
			"from": [13.35, -0.1, 13.9],
			"to": [13.75, 5.1, 14.2],
			"rotation": {"angle": -22.5, "axis": "y", "origin": [13.57262, 10.07738, 14.05]},
			"faces": {
				"north": {"uv": [7.75, 1, 8.5, 15], "texture": "#0"},
				"east": {"uv": [7.75, 1, 8.5, 15], "texture": "#0"},
				"south": {"uv": [7.75, 1, 8.5, 15], "texture": "#0"},
				"west": {"uv": [7.75, 1, 8.5, 15], "texture": "#0"},
				"up": {"uv": [7.75, 1, 8.5, 2.5], "texture": "#0"},
				"down": {"uv": [13, 0, 16, 3.25], "texture": "#0"}
			}
		},
		{
			"from": [13.475, -0.4, 11.225],
			"to": [13.475, 7.4, 16.575],
			"rotation": {"angle": -22.5, "axis": "y", "origin": [13.57262, 10.07738, 14.05]},
			"faces": {
				"north": {"uv": [6, 4, 10.5, 12.75], "texture": "#2"},
				"east": {"uv": [0, 0, 16, 16], "texture": "#4"},
				"south": {"uv": [6, 4, 10.5, 12.75], "texture": "#2"},
				"west": {"uv": [0, 0, 16, 16], "texture": "#3"},
				"up": {"uv": [6, 4, 10.5, 6.75], "rotation": 270, "texture": "#2"},
				"down": {"uv": [13, 0, 16, 3.25], "rotation": 90, "texture": "#0"}
			}
		},
		{
			"from": [13.475, 7.2, 11.725],
			"to": [13.475, 13, 16.075],
			"rotation": {"angle": -22.5, "axis": "y", "origin": [13.57262, 10.07738, 14.05]},
			"faces": {
				"north": {"uv": [6, 4, 10.5, 12.75], "texture": "#2"},
				"east": {"uv": [0, 0, 16, 16], "texture": "#4"},
				"south": {"uv": [6, 4, 10.5, 12.75], "texture": "#2"},
				"west": {"uv": [0, 0, 16, 16], "texture": "#3"},
				"up": {"uv": [6, 4, 10.5, 6.75], "rotation": 270, "texture": "#2"},
				"down": {"uv": [13, 0, 16, 3.25], "rotation": 90, "texture": "#0"}
			}
		},
		{
			"from": [10.75, -0.4, 14.15],
			"to": [16.1, 7.4, 14.15],
			"rotation": {"angle": -22.5, "axis": "y", "origin": [13.57262, 10.07738, 14.05]},
			"faces": {
				"north": {"uv": [0, 0, 16, 16], "texture": "#4"},
				"east": {"uv": [6, 4, 10.5, 12.75], "texture": "#2"},
				"south": {"uv": [0, 0, 16, 16], "texture": "#3"},
				"west": {"uv": [6, 4, 10.5, 12.75], "texture": "#2"},
				"up": {"uv": [6, 4, 10.5, 6.75], "rotation": 180, "texture": "#2"},
				"down": {"uv": [13, 0, 16, 3.25], "rotation": 180, "texture": "#0"}
			}
		},
		{
			"from": [11.25, 7.1, 14.15],
			"to": [15.6, 13.6, 14.15],
			"rotation": {"angle": -22.5, "axis": "y", "origin": [13.57262, 10.07738, 14.05]},
			"faces": {
				"north": {"uv": [0, 0, 16, 16], "texture": "#4"},
				"east": {"uv": [6, 4, 10.5, 12.75], "texture": "#2"},
				"south": {"uv": [0, 0, 16, 16], "texture": "#3"},
				"west": {"uv": [6, 4, 10.5, 12.75], "texture": "#2"},
				"up": {"uv": [6, 4, 10.5, 6.75], "rotation": 180, "texture": "#2"},
				"down": {"uv": [13, 0, 16, 3.25], "rotation": 180, "texture": "#0"}
			}
		},
		{
			"from": [13.675, -0.4, 11.525],
			"to": [13.675, 7.4, 16.875],
			"rotation": {"angle": -22.5, "axis": "y", "origin": [13.57262, 10.07738, 14.05]},
			"faces": {
				"north": {"uv": [6, 4, 10.5, 12.75], "texture": "#2"},
				"east": {"uv": [0, 0, 16, 16], "texture": "#3"},
				"south": {"uv": [6, 4, 10.5, 12.75], "texture": "#2"},
				"west": {"uv": [0, 0, 16, 16], "texture": "#4"},
				"up": {"uv": [10.5, 6.75, 6, 4], "rotation": 270, "texture": "#2"},
				"down": {"uv": [16, 3.25, 13, 0], "rotation": 90, "texture": "#0"}
			}
		},
		{
			"from": [13.675, 7.2, 12.025],
			"to": [13.675, 13, 16.375],
			"rotation": {"angle": -22.5, "axis": "y", "origin": [13.57262, 10.07738, 14.05]},
			"faces": {
				"north": {"uv": [6, 4, 10.5, 12.75], "texture": "#2"},
				"east": {"uv": [0, 0, 16, 16], "texture": "#3"},
				"south": {"uv": [6, 4, 10.5, 12.75], "texture": "#2"},
				"west": {"uv": [0, 0, 16, 16], "texture": "#4"},
				"up": {"uv": [10.5, 6.75, 6, 4], "rotation": 270, "texture": "#2"},
				"down": {"uv": [16, 3.25, 13, 0], "rotation": 90, "texture": "#0"}
			}
		},
		{
			"from": [11.05, -0.4, 13.95],
			"to": [16.4, 7.4, 13.95],
			"rotation": {"angle": -22.5, "axis": "y", "origin": [13.57262, 10.07738, 14.05]},
			"faces": {
				"north": {"uv": [0, 0, 16, 16], "texture": "#3"},
				"east": {"uv": [6, 4, 10.5, 12.75], "texture": "#2"},
				"south": {"uv": [0, 0, 16, 16], "texture": "#4"},
				"west": {"uv": [6, 4, 10.5, 12.75], "texture": "#2"},
				"up": {"uv": [10.5, 6.75, 6, 4], "rotation": 180, "texture": "#2"},
				"down": {"uv": [16, 3.25, 13, 0], "rotation": 180, "texture": "#0"}
			}
		},
		{
			"from": [11.55, 7.1, 13.95],
			"to": [15.9, 13.6, 13.95],
			"rotation": {"angle": -22.5, "axis": "y", "origin": [13.57262, 10.07738, 14.05]},
			"faces": {
				"north": {"uv": [0, 0, 16, 16], "texture": "#3"},
				"east": {"uv": [6, 4, 10.5, 12.75], "texture": "#2"},
				"south": {"uv": [0, 0, 16, 16], "texture": "#4"},
				"west": {"uv": [6, 4, 10.5, 12.75], "texture": "#2"},
				"up": {"uv": [10.5, 6.75, 6, 4], "rotation": 180, "texture": "#2"},
				"down": {"uv": [16, 3.25, 13, 0], "rotation": 180, "texture": "#0"}
			}
		}
	],
	"display": {
		"thirdperson_righthand": {
			"rotation": [54, 0, 0],
			"translation": [-2.5, -1, 0.75]
		},
		"thirdperson_lefthand": {
			"rotation": [42, 0, 0],
			"translation": [0.5, -0.75, 1]
		},
		"firstperson_righthand": {
			"rotation": [-18, 0, 0],
			"translation": [-2, -3, 1.75],
			"scale": [1.66, 1.66, 1.66]
		},
		"firstperson_lefthand": {
			"rotation": [-11, 0, 0],
			"translation": [2.75, -2.75, 1.75],
			"scale": [1.66, 1.66, 1.66]
		},
		"ground": {
			"translation": [0, 4.25, 0]
		},
		"gui": {
			"translation": [0.75, 1, 0]
		},
		"head": {
			"translation": [0, -10.5, -3.25],
			"scale": [4, 3.95, 3.95]
		},
		"fixed": {
			"translation": [0.5, 0.5, 0]
		}
	},
	"groups": [
		{
			"name": "group",
			"origin": [17, 14.5, 15],
			"children": [0, 1, 2, 3, 4, 5, 6, 7, 8, 9, 10, 11, 12, 13, 14, 15, 16, 17, 18, 19, 20]
		},
		{
			"name": "group",
			"origin": [17, 14.5, 15],
			"children": [21, 22, 23, 24, 25, 26, 27, 28, 29, 30, 31, 32, 33, 34, 35, 36, 37, 38, 39, 40, 41]
		},
		{
			"name": "group",
			"origin": [17, 14.5, 15],
			"children": [42, 43, 44, 45, 46, 47, 48, 49, 50, 51, 52, 53, 54, 55, 56, 57, 58, 59, 60, 61, 62]
		},
		{
			"name": "group",
			"origin": [17, 14.5, 15],
			"children": [63, 64, 65, 66, 67, 68, 69, 70, 71, 72, 73, 74, 75, 76, 77, 78, 79, 80, 81, 82, 83]
		},
		{
			"name": "group",
			"origin": [17, 14.5, 15],
			"children": [84, 85, 86, 87, 88, 89, 90, 91, 92, 93, 94, 95, 96, 97, 98, 99, 100, 101, 102, 103, 104]
		},
		{
			"name": "group",
			"origin": [17, 14.5, 15],
			"children": [105, 106, 107, 108, 109, 110, 111, 112, 113, 114, 115, 116, 117, 118, 119, 120, 121, 122, 123, 124, 125]
		},
		{
			"name": "group",
			"origin": [17, 14.5, 15],
			"children": [126, 127, 128, 129, 130, 131, 132, 133, 134, 135, 136, 137, 138, 139, 140, 141, 142, 143, 144, 145, 146]
		},
		{
			"name": "group",
			"origin": [17, 14.5, 15],
			"children": [147, 148, 149, 150, 151, 152, 153, 154, 155, 156, 157, 158, 159, 160, 161, 162, 163, 164, 165, 166, 167]
		},
		{
			"name": "group",
			"origin": [17, 14.5, 15],
			"children": [168, 169, 170, 171, 172, 173, 174, 175, 176, 177, 178, 179, 180, 181, 182, 183, 184, 185, 186, 187, 188]
		}
	]
}